src/soc/hazard_control_unit/hazard_control_unit.v
/*
Module - Hazard Control Unit.
Author - Zach Walden
Last Changed - 3/28/22, 4/4/22
Description - This Module is a finite state machine that controls the state of operation of the pipeline.
Parameters -
*/

module hazard_control_unit(
	input clock,
	input nreset,
	//Inputs
	input ret,
	input halt,
	input fetch_stl_req,
	input dec_stl_req,
	input interrupt,
	input [13:0] interrupt_vector_address,
	//Outputs
	output reg stall_fetch = 0,
	output reg stall_decode = 0,
	output reg [2:0] prog_cntr_load_sel = 0,
	output reg inst_word_sel = 0,
	output reg [31:0] new_inst_word = 0,
	output reg [13:0] prog_cntr_int_addr = 0,
	//State
	output [2:0] control_state
);

	reg [2:0] state = 0, next_state = 0;

	always @ (negedge clock)
	begin
		if(nreset == 1'b0)
		begin
			state <= 0;
		end
		else
		begin
			state <= next_state;
		end
	end

	always @ (*)
	begin
		case(state)
			//Normal 4'b0000
			3'h0 :
			begin
				//Outputs
				stall_fetch <= 1'b0;
				stall_decode <= 1'b0;
				prog_cntr_load_sel <= 3'b001;
				inst_word_sel <= 1'b0;
				new_inst_word <= 32'h00000000;
				prog_cntr_int_addr <= 14'h0000;
				if(ret == 1'b1)
				begin
					next_state <= 3'b101;
				end
				else if(halt == 1'b1)
				begin
					next_state <= 3'b001;
				end
				else if(fetch_stl_req == 1'b1)
				begin
					next_state <= 3'b011;
				end
				else if(dec_stl_req == 1'b1)
				begin
					next_state <= 3'b100;
				end
				else if(interrupt == 1'b1)
				begin
					next_state <= 3'b010;
				end
				else
				begin
					next_state <= 3'b000;
				end
			end
			//Halt 4'b0001
			3'h1 :
			begin
				//Outputs
				stall_fetch <= 1'b1;
				stall_decode <= 1'b0;
				prog_cntr_load_sel <= 3'b001;
				inst_word_sel <= 1'b1;
				new_inst_word <= 32'h00000000;
				prog_cntr_int_addr <= 14'h0000;
				if(interrupt == 1'b1)
				begin
					next_state <= 3'b010;
				end
				else
				begin
					next_state <= 3'b001;
				end
			end
			//Interrupt 4'b0010
			3'h2 :
			begin
				//Outputs
				stall_fetch <= 1'b0;
				stall_decode <= 1'b0;
				prog_cntr_load_sel <= 3'b010;
				inst_word_sel <= 1'b1;
				new_inst_word[31:18] <= interrupt_vector_address;
				new_inst_word[17:0] <= 18'h00042;
				prog_cntr_int_addr <= interrupt_vector_address;
				//Go To Normal
				next_state <= 3'b000;
			end
			//Stall Fetch 4'b0011
			3'h3 :
			begin
				//Outputs
				stall_fetch <= 1'b1;
				stall_decode <= 1'b0;
				prog_cntr_load_sel <= 3'b001;
				inst_word_sel <= 1'b1;
				new_inst_word <= 32'h00000000;
				prog_cntr_int_addr <= 14'h0000;

				if(interrupt == 1'b1)
				begin
					next_state <= 3'b010;
				end
				else
				begin
					next_state <= 3'b000;
				end
			end
			//Stall Decode 4'b0100
			3'h4 :
			begin
				//Outputs
				stall_fetch <= 1'b1;
				stall_decode <= 1'b1;
				prog_cntr_load_sel <= 3'b001;
				inst_word_sel <= 1'b1;
				new_inst_word <= 32'h00000000;
				prog_cntr_int_addr <= 14'h0000;
				if(interrupt == 1'b1)
				begin
					next_state <= 3'b010;
				end
				else
				begin
					next_state <= 3'b000;
				end
			end
			//Return 1 4'b0101
			3'h5 :
			begin
				//Outputs
				stall_fetch <= 1'b1;
				stall_decode <= 1'b0;
				prog_cntr_load_sel <= 3'b001;
				inst_word_sel <= 1'b1;
				new_inst_word <= 32'h00000000;
				prog_cntr_int_addr <= 14'h0000;
				//To ret 2
				next_state <= 3'b110;
			end
			//Return 2 4'b0110
			3'h6 :
			begin
				//Outputs
				stall_fetch <= 1'b1;
				stall_decode <= 1'b0;
				prog_cntr_load_sel <= 3'b001;
				inst_word_sel <= 1'b1;
				new_inst_word <= 32'h00000000;
				prog_cntr_int_addr <= 14'h0000;
				//To Return 3
				next_state <= 3'b111;
			end
			//Return 3 4'b111
			3'h7 :
			begin
				//Outputs
				stall_fetch <= 1'b1;
				stall_decode <= 1'b0;
				prog_cntr_load_sel <= 3'b100;
				inst_word_sel <= 1'b1;
				new_inst_word <= 32'h00000000;
				prog_cntr_int_addr <= 14'h0000;
				//To Normal
				next_state <= 3'b000;
			end
		endcase
	end

	assign control_state = state;


// the "macro" to dump signals
`ifdef COCOTB_SIM
initial begin
  $dumpfile ("hazard_control_unit.vcd");
  $dumpvars (0, hazard_control_unit);
  #1;
end
`endif

endmodule

src/soc/hazard_control_unit/hazard_control_unit.vcd
$date
	Mon Apr  4 22:07:52 2022
$end
$version
	Icarus Verilog
$end
$timescale
	1ps
$end
$scope module hazard_control_unit $end
$var wire 1 ! clock $end
$var wire 3 " control_state [2:0] $end
$var wire 1 # dec_stl_req $end
$var wire 1 $ fetch_stl_req $end
$var wire 1 % halt $end
$var wire 1 & interrupt $end
$var wire 14 ' interrupt_vector_address [13:0] $end
$var wire 1 ( nreset $end
$var wire 1 ) ret $end
$var reg 1 * inst_word_sel $end
$var reg 32 + new_inst_word [31:0] $end
$var reg 3 , next_state [2:0] $end
$var reg 14 - prog_cntr_int_addr [13:0] $end
$var reg 3 . prog_cntr_load_sel [2:0] $end
$var reg 1 / stall_decode $end
$var reg 1 0 stall_fetch $end
$var reg 3 1 state [2:0] $end
$upscope $end
$enddefinitions $end
#0
$dumpvars
b0 1
00
0/
b1 .
b0 -
b0 ,
b0 +
0*
0)
1(
b11111111111111 '
0&
0%
0$
0#
b0 "
1!
$end
#5000
0!
#10000
b101 ,
1)
1!
#15000
b110 ,
1*
10
b101 "
b101 1
0!
#20000
0)
1&
1!
#25000
b111 ,
b110 "
b110 1
0!
#30000
1!
#35000
b0 ,
b100 .
b111 "
b111 1
0!
#40000
1!
#45000
b10 ,
0*
b1 .
00
b0 "
b0 1
0!
#50000
1!
#55000
b0 ,
b11111111111111 -
b11111111111111000000000001000010 +
1*
b10 .
b10 "
b10 1
0!
#60000
0&
1%
1!
#65000
b1 ,
b0 -
b0 +
0*
b1 .
b0 "
b0 1
0!
#70000
1!
#75000
1*
10
b1 "
b1 1
0!
#80000
0%
1$
1!
#85000
0!
#90000
0$
1#
1!
#95000
0!
#100000
0#
1)
1!
#105000
0!
#110000
b10 ,
0)
1&
1!
#115000
b0 ,
b11111111111111 -
b11111111111111000000000001000010 +
b10 .
00
b10 "
b10 1
0!
