backup/pipeline/stages/memory/sfr_file/sfr_file.v
/*
Module - Special Function Register File
Author - Zach Walden
Last Changed - 2/18/21
Description - 32 x 8 special purpose register file. This module has a single read and write port. What differentiates this module from the general purpose register file is that every single register is exposed to the entire peripheral system for reading at any time.This will be use for memory addressing, interupt control, and peripheral control. These functions, besides memory addressing, need not be defined during the design of the main CPU.
Parameters -
*/

module sfr_file(
	input clock,
	input nreset,
	input [1:0] wren,
	input [4:0] wr_addr,
	input [7:0] write_data,
	input [4:0] rd_addr,
	output [7:0] read_data,
	output [15:0] w_ptr,
	output [15:0] x_ptr,
	output [15:0] y_ptr,
	output [15:0] z_ptr,
	output fb_segment,
	output [255:0] sfr_file_out
);

	integer i;

	reg [7:0] sfr_array [0:31];
	reg [7:0] out_data = 0;

	initial
	begin
		for(i=0;i<32;i=i+1)
		begin
			sfr_array[i] <= 0;
		end
	end


	always @ (negedge clock)
	begin
		if(nreset == 1'b1)
		begin
			for(i=0;i<32;i=i+1)
			begin
				sfr_array[i] <= 0;
			end
		end
		else
		begin
			//wren[0] is write enable
			if(wren == 2'b01)
			begin
				sfr_array[wr_addr] <= write_data;
			end
			else if(wren == 2'b10)
			begin
				out_data <= sfr_array[rd_addr];
			end
			else
			begin
				out_data <= 8'h00;
			end
		end
	end

	assign sfr_file_out[7:0] = sfr_array[0];
	assign sfr_file_out[15:8] = sfr_array[1];
	assign sfr_file_out[23:16] = sfr_array[2];
	assign sfr_file_out[31:24] = sfr_array[3];
	assign sfr_file_out[40:32] = sfr_array[4];
	assign sfr_file_out[48:41] = sfr_array[5];
	assign sfr_file_out[56:49] = sfr_array[6];
	assign sfr_file_out[63:57] = sfr_array[7];
	assign sfr_file_out[71:64] = sfr_array[8];
	assign sfr_file_out[79:72] = sfr_array[9];
	assign sfr_file_out[87:80] = sfr_array[10];
	assign sfr_file_out[95:88] = sfr_array[11];
	assign sfr_file_out[103:96] = sfr_array[12];
	assign sfr_file_out[111:104] = sfr_array[13];
	assign sfr_file_out[119:112] = sfr_array[14];
	assign sfr_file_out[127:120] = sfr_array[15];
	assign sfr_file_out[135:128] = sfr_array[16];
	assign sfr_file_out[143:136] = sfr_array[17];
	assign sfr_file_out[151:144] = sfr_array[18];
	assign sfr_file_out[159:152] = sfr_array[19];
	assign sfr_file_out[167:160] = sfr_array[20];
	assign sfr_file_out[175:168] = sfr_array[21];
	assign sfr_file_out[183:176] = sfr_array[22];
	assign sfr_file_out[191:184] = sfr_array[23];
	assign sfr_file_out[199:192] = sfr_array[24];
	assign sfr_file_out[207:200] = sfr_array[25];
	assign sfr_file_out[215:208] = sfr_array[26];
	assign sfr_file_out[223:216] = sfr_array[27];
	assign sfr_file_out[231:224] = sfr_array[28];
	assign sfr_file_out[239:232] = sfr_array[29];
	assign sfr_file_out[247:240] = sfr_array[30];
	assign sfr_file_out[255:248] = sfr_array[31];

	assign w_ptr[7:0] = sfr_array[0];
	assign w_ptr[15:8] = sfr_array[1];
	assign x_ptr[7:0] = sfr_array[2];
	assign x_ptr[15:8] = sfr_array[3];
	assign y_ptr[7:0] = sfr_array[4];
	assign y_ptr[15:8] = sfr_array[5];
	assign z_ptr[7:0] = sfr_array[6];
	assign z_ptr[15:8] = sfr_array[7];

	assign fb_segment = sfr_array[8][1];

	assign read_data = out_data;

// the "macro" to dump signals
`ifdef COCOTB_SIM
initial begin
  $dumpfile ("sfr_file.vcd");
  $dumpvars (0, sfr_file);
  #1;
end
`endif
endmodule

backup/pipeline/stages/memory/sfr_file/sfr_file.vcd
$date
	Fri Feb 18 23:51:08 2022
$end
$version
	Icarus Verilog
$end
$timescale
	1ps
$end
$scope module sfr_file $end
$var wire 1 ! clock $end
$var wire 1 " nreset $end
$var wire 5 # rd_addr [4:0] $end
$var wire 8 $ read_data [7:0] $end
$var wire 5 % wr_addr [4:0] $end
$var wire 2 & wren [1:0] $end
$var wire 8 ' write_data [7:0] $end
$var wire 16 ( z_ptr [15:0] $end
$var wire 16 ) y_ptr [15:0] $end
$var wire 16 * x_ptr [15:0] $end
$var wire 16 + w_ptr [15:0] $end
$var wire 256 , sfr_file_out [255:0] $end
$var wire 1 - fb_segment $end
$var reg 8 . out_data [7:0] $end
$var integer 32 / i [31:0] $end
$upscope $end
$enddefinitions $end
#0
$dumpvars
b100000 /
b0 .
0-
b0 ,
b0 +
b0 *
b0 )
b0 (
bz '
bz &
bz %
b0 $
bz #
0"
1!
$end
#5000
1"
0!
#10000
1!
#15000
b10 &
b0 #
b100000 /
0!
#20000
1!
#25000
b1 #
b100000 /
0!
#30000
1!
#35000
b10 #
b100000 /
0!
#40000
1!
#45000
b11 #
b100000 /
0!
#50000
1!
#55000
b100 #
b100000 /
0!
#60000
1!
#65000
b101 #
b100000 /
0!
#70000
1!
#75000
b110 #
b100000 /
0!
#80000
1!
#85000
b111 #
b100000 /
0!
#90000
1!
#95000
b1000 #
b100000 /
0!
#100000
1!
#105000
b1001 #
b100000 /
0!
#110000
1!
#115000
b1010 #
b100000 /
0!
#120000
1!
#125000
b1011 #
b100000 /
0!
#130000
1!
#135000
b1100 #
b100000 /
0!
#140000
1!
#145000
b1101 #
b100000 /
0!
#150000
1!
#155000
b1110 #
b100000 /
0!
#160000
1!
#165000
b1111 #
b100000 /
0!
#170000
1!
#175000
b10000 #
b100000 /
0!
#180000
1!
#185000
b10001 #
b100000 /
0!
#190000
1!
#195000
b10010 #
b100000 /
0!
#200000
1!
#205000
b10011 #
b100000 /
0!
#210000
1!
#215000
b10100 #
b100000 /
0!
#220000
1!
#225000
b10101 #
b100000 /
0!
#230000
1!
#235000
b10110 #
b100000 /
0!
#240000
1!
#245000
b10111 #
b100000 /
0!
#250000
1!
#255000
b11000 #
b100000 /
0!
#260000
1!
#265000
b11001 #
b100000 /
0!
#270000
1!
#275000
b11010 #
b100000 /
0!
#280000
1!
#285000
b11011 #
b100000 /
0!
#290000
1!
#295000
b11100 #
b100000 /
0!
#300000
1!
#305000
b11101 #
b100000 /
0!
#310000
1!
#315000
b11110 #
b100000 /
0!
#320000
1!
#325000
b11111 #
b100000 /
0!
#330000
1!
#335000
b100000 /
0!
