src/soc/timer/timer.v
/*
Module - Timer
Author - Zach Walden
Last Changed - 4/16/22
Description - 64-Bit Timer with an enable bit along with a clear bit. Synchronous Active Low Reset.
Parameters -
*/

module timer(
	input clock,
	input nreset,
	input [7:0] control_reg, //<7> ,<6> ,<5> ,<4> ,<3> ,<2> ,<1> Clear 1 = Reset, 0 = Normal,<0> Timer Enable 1 = run, 0 = stop
	output reg [63:0] timer_value = 0
);

	wire [63:0] timer_inc;

	always @ (posedge clock)
	begin
		if(nreset == 1'b0 || control_reg[1] == 1'b1)
		begin
			timer_value <= 0;
		end
		else if(control_reg[0] == 1'b1)
		begin
			timer_value <= timer_inc;
		end
	end

	assign timer_inc = timer_value + 1;

// the "macro" to dump signals
`ifdef COCOTB_SIM
initial begin
  $dumpfile ("timer.vcd");
  $dumpvars (0, timer);
  #1;
end
`endif
endmodule

src/Waveforms/cpu/timer/timer.vcd
$date
	Sat Apr 16 13:33:02 2022
$end
$version
	Icarus Verilog
$end
$timescale
	1ps
$end
$scope module timer $end
$var wire 1 ! clock $end
$var wire 8 " control_reg [7:0] $end
$var wire 1 # nreset $end
$var wire 64 $ timer_inc [63:0] $end
$var reg 64 % timer_value [63:0] $end
$upscope $end
$enddefinitions $end
#0
$dumpvars
b1 %
b10 $
1#
b1 "
1!
$end
#5000
0!
#10000
b11 $
b10 %
1!
#15000
0!
#20000
b100 $
b11 %
1!
#25000
0!
#30000
b101 $
b100 %
1!
#35000
0!
#40000
b110 $
b101 %
1!
#45000
0!
#50000
b111 $
b110 %
1!
#55000
0!
#60000
b1000 $
b111 %
1!
#65000
0!
#70000
b1001 $
b1000 %
1!
#75000
0!
#80000
b1010 $
b1001 %
1!
#85000
0!
#90000
b1011 $
b1010 %
1!
#95000
0!
#100000
b1100 $
b1011 %
1!
#105000
0!
#110000
b1101 $
b1100 %
1!
#115000
0!
#120000
b1110 $
b1101 %
1!
#125000
0!
#130000
b1111 $
b1110 %
1!
#135000
0!
#140000
b10000 $
b1111 %
1!
#145000
0!
#150000
b10001 $
b10000 %
1!
#155000
0!
#160000
b10010 $
b10001 %
1!
#165000
0!
#170000
b10011 $
b10010 %
1!
#175000
0!
#180000
b10100 $
b10011 %
1!
#185000
0!
#190000
b10101 $
b10100 %
1!
#195000
0!
#200000
b10110 $
b10101 %
1!
#205000
0!
#210000
b10111 $
b10110 %
1!
#215000
0!
#220000
b11000 $
b10111 %
1!
#225000
0!
#230000
b11001 $
b11000 %
1!
#235000
0!
#240000
b11010 $
b11001 %
1!
#245000
0!
#250000
b11011 $
b11010 %
1!
#255000
0!
#260000
b11100 $
b11011 %
1!
#265000
0!
#270000
b11101 $
b11100 %
1!
#275000
0!
#280000
b11110 $
b11101 %
1!
#285000
0!
#290000
b11111 $
b11110 %
1!
#295000
0!
#300000
b100000 $
b11111 %
1!
#305000
0!
#310000
b100001 $
b100000 %
1!
#315000
0!
#320000
b100010 $
b100001 %
1!
#325000
0!
#330000
b100011 $
b100010 %
1!
#335000
0!
#340000
b100100 $
b100011 %
1!
#345000
0!
#350000
b100101 $
b100100 %
1!
#355000
0!
#360000
b100110 $
b100101 %
1!
#365000
0!
#370000
b100111 $
b100110 %
1!
#375000
0!
#380000
b101000 $
b100111 %
1!
#385000
0!
#390000
b101001 $
b101000 %
1!
#395000
0!
#400000
b101010 $
b101001 %
1!
#405000
0!
#410000
b101011 $
b101010 %
1!
#415000
0!
#420000
b101100 $
b101011 %
1!
#425000
0!
#430000
b101101 $
b101100 %
1!
#435000
0!
#440000
b101110 $
b101101 %
1!
#445000
0!
#450000
b101111 $
b101110 %
1!
#455000
0!
#460000
b110000 $
b101111 %
1!
#465000
0!
#470000
b110001 $
b110000 %
1!
#475000
0!
#480000
b110010 $
b110001 %
1!
#485000
0!
#490000
b110011 $
b110010 %
1!
#495000
0!
#500000
b110100 $
b110011 %
1!
#505000
0!
#510000
b110101 $
b110100 %
1!
#515000
0!
#520000
b110110 $
b110101 %
1!
#525000
0!
#530000
b110111 $
b110110 %
1!
#535000
0!
#540000
b111000 $
b110111 %
1!
#545000
0!
#550000
b111001 $
b111000 %
1!
#555000
0!
#560000
b111010 $
b111001 %
1!
#565000
0!
#570000
b111011 $
b111010 %
1!
#575000
0!
#580000
b111100 $
b111011 %
1!
#585000
0!
#590000
b111101 $
b111100 %
1!
#595000
0!
#600000
b111110 $
b111101 %
1!
#605000
0!
#610000
b111111 $
b111110 %
1!
#615000
0!
#620000
b1000000 $
b111111 %
1!
#625000
0!
#630000
b1000001 $
b1000000 %
1!
#635000
0!
#640000
b1000010 $
b1000001 %
1!
#645000
0!
#650000
b1000011 $
b1000010 %
1!
#655000
0!
#660000
b1000100 $
b1000011 %
1!
#665000
0!
#670000
b1000101 $
b1000100 %
1!
#675000
0!
#680000
b1000110 $
b1000101 %
1!
#685000
0!
#690000
b1000111 $
b1000110 %
1!
#695000
0!
#700000
b1001000 $
b1000111 %
1!
#705000
0!
#710000
b1001001 $
b1001000 %
1!
#715000
0!
#720000
b1001010 $
b1001001 %
1!
#725000
0!
#730000
b1001011 $
b1001010 %
1!
#735000
0!
#740000
b1001100 $
b1001011 %
1!
#745000
0!
#750000
b1001101 $
b1001100 %
1!
#755000
0!
#760000
b1001110 $
b1001101 %
1!
#765000
0!
#770000
b1001111 $
b1001110 %
1!
#775000
0!
#780000
b1010000 $
b1001111 %
1!
#785000
0!
#790000
b1010001 $
b1010000 %
1!
#795000
0!
#800000
b1010010 $
b1010001 %
1!
#805000
0!
#810000
b1010011 $
b1010010 %
1!
#815000
0!
#820000
b1010100 $
b1010011 %
1!
#825000
0!
#830000
b1010101 $
b1010100 %
1!
#835000
0!
#840000
b1010110 $
b1010101 %
1!
#845000
0!
#850000
b1010111 $
b1010110 %
1!
#855000
0!
#860000
b1011000 $
b1010111 %
1!
#865000
0!
#870000
b1011001 $
b1011000 %
1!
#875000
0!
#880000
b1011010 $
b1011001 %
1!
#885000
0!
#890000
b1011011 $
b1011010 %
1!
#895000
0!
#900000
b1011100 $
b1011011 %
1!
#905000
0!
#910000
b1011101 $
b1011100 %
1!
#915000
0!
#920000
b1011110 $
b1011101 %
1!
#925000
0!
#930000
b1011111 $
b1011110 %
1!
#935000
0!
#940000
b1100000 $
b1011111 %
1!
#945000
0!
#950000
b1100001 $
b1100000 %
1!
#955000
0!
#960000
b1100010 $
b1100001 %
1!
#965000
0!
#970000
b1100011 $
b1100010 %
1!
#975000
0!
#980000
b1100100 $
b1100011 %
1!
#985000
0!
#990000
b1100101 $
b1100100 %
1!
#995000
0!
#1000000
b1100110 $
b1100101 %
1!
#1005000
0!
#1010000
b1100111 $
b1100110 %
1!
#1015000
0!
#1020000
b1101000 $
b1100111 %
1!
#1025000
0!
#1030000
b1101001 $
b1101000 %
1!
#1035000
0!
#1040000
b1101010 $
b1101001 %
1!
#1045000
0!
#1050000
b1101011 $
b1101010 %
1!
#1055000
0!
#1060000
b1101100 $
b1101011 %
1!
#1065000
0!
#1070000
b1101101 $
b1101100 %
1!
#1075000
0!
#1080000
b1101110 $
b1101101 %
1!
#1085000
0!
#1090000
b1101111 $
b1101110 %
1!
#1095000
0!
#1100000
b1110000 $
b1101111 %
1!
#1105000
0!
#1110000
b1110001 $
b1110000 %
1!
#1115000
0!
#1120000
b1110010 $
b1110001 %
1!
#1125000
0!
#1130000
b1110011 $
b1110010 %
1!
#1135000
0!
#1140000
b1110100 $
b1110011 %
1!
#1145000
0!
#1150000
b1110101 $
b1110100 %
1!
#1155000
0!
#1160000
b1110110 $
b1110101 %
1!
#1165000
0!
#1170000
b1110111 $
b1110110 %
1!
#1175000
0!
#1180000
b1111000 $
b1110111 %
1!
#1185000
0!
#1190000
b1111001 $
b1111000 %
1!
#1195000
0!
#1200000
b1111010 $
b1111001 %
1!
#1205000
0!
#1210000
b1111011 $
b1111010 %
1!
#1215000
0!
#1220000
b1111100 $
b1111011 %
1!
#1225000
0!
#1230000
b1111101 $
b1111100 %
1!
#1235000
0!
#1240000
b1111110 $
b1111101 %
1!
#1245000
0!
#1250000
b1111111 $
b1111110 %
1!
#1255000
0!
#1260000
b10000000 $
b1111111 %
1!
#1265000
0!
#1270000
b10000001 $
b10000000 %
1!
#1275000
0!
#1280000
b10000010 $
b10000001 %
1!
#1285000
0!
#1290000
b10000011 $
b10000010 %
1!
#1295000
0!
#1300000
b10000100 $
b10000011 %
1!
#1305000
0!
#1310000
b10000101 $
b10000100 %
1!
#1315000
0!
#1320000
b10000110 $
b10000101 %
1!
#1325000
0!
#1330000
b10000111 $
b10000110 %
1!
#1335000
0!
#1340000
b10001000 $
b10000111 %
1!
#1345000
0!
#1350000
b10001001 $
b10001000 %
1!
#1355000
0!
#1360000
b10001010 $
b10001001 %
1!
#1365000
0!
#1370000
b10001011 $
b10001010 %
1!
#1375000
0!
#1380000
b10001100 $
b10001011 %
1!
#1385000
0!
#1390000
b10001101 $
b10001100 %
1!
#1395000
0!
#1400000
b10001110 $
b10001101 %
1!
#1405000
0!
#1410000
b10001111 $
b10001110 %
1!
#1415000
0!
#1420000
b10010000 $
b10001111 %
1!
#1425000
0!
#1430000
b10010001 $
b10010000 %
1!
#1435000
0!
#1440000
b10010010 $
b10010001 %
1!
#1445000
0!
#1450000
b10010011 $
b10010010 %
1!
#1455000
0!
#1460000
b10010100 $
b10010011 %
1!
#1465000
0!
#1470000
b10010101 $
b10010100 %
1!
#1475000
0!
#1480000
b10010110 $
b10010101 %
1!
#1485000
0!
#1490000
b10010111 $
b10010110 %
1!
#1495000
0!
#1500000
b10011000 $
b10010111 %
1!
#1505000
0!
#1510000
b10011001 $
b10011000 %
1!
#1515000
0!
#1520000
b10011010 $
b10011001 %
1!
#1525000
0!
#1530000
b10011011 $
b10011010 %
1!
#1535000
0!
#1540000
b10011100 $
b10011011 %
1!
#1545000
0!
#1550000
b10011101 $
b10011100 %
1!
#1555000
0!
#1560000
b10011110 $
b10011101 %
1!
#1565000
0!
#1570000
b10011111 $
b10011110 %
1!
#1575000
0!
#1580000
b10100000 $
b10011111 %
1!
#1585000
0!
#1590000
b10100001 $
b10100000 %
1!
#1595000
0!
#1600000
b10100010 $
b10100001 %
1!
#1605000
0!
#1610000
b10100011 $
b10100010 %
1!
#1615000
0!
#1620000
b10100100 $
b10100011 %
1!
#1625000
0!
#1630000
b10100101 $
b10100100 %
1!
#1635000
0!
#1640000
b10100110 $
b10100101 %
1!
#1645000
0!
#1650000
b10100111 $
b10100110 %
1!
#1655000
0!
#1660000
b10101000 $
b10100111 %
1!
#1665000
0!
#1670000
b10101001 $
b10101000 %
1!
#1675000
0!
#1680000
b10101010 $
b10101001 %
1!
#1685000
0!
#1690000
b10101011 $
b10101010 %
1!
#1695000
0!
#1700000
b10101100 $
b10101011 %
1!
#1705000
0!
#1710000
b10101101 $
b10101100 %
1!
#1715000
0!
#1720000
b10101110 $
b10101101 %
1!
#1725000
0!
#1730000
b10101111 $
b10101110 %
1!
#1735000
0!
#1740000
b10110000 $
b10101111 %
1!
#1745000
0!
#1750000
b10110001 $
b10110000 %
1!
#1755000
0!
#1760000
b10110010 $
b10110001 %
1!
#1765000
0!
#1770000
b10110011 $
b10110010 %
1!
#1775000
0!
#1780000
b10110100 $
b10110011 %
1!
#1785000
0!
#1790000
b10110101 $
b10110100 %
1!
#1795000
0!
#1800000
b10110110 $
b10110101 %
1!
#1805000
0!
#1810000
b10110111 $
b10110110 %
1!
#1815000
0!
#1820000
b10111000 $
b10110111 %
1!
#1825000
0!
#1830000
b10111001 $
b10111000 %
1!
#1835000
0!
#1840000
b10111010 $
b10111001 %
1!
#1845000
0!
#1850000
b10111011 $
b10111010 %
1!
#1855000
0!
#1860000
b10111100 $
b10111011 %
1!
#1865000
0!
#1870000
b10111101 $
b10111100 %
1!
#1875000
0!
#1880000
b10111110 $
b10111101 %
1!
#1885000
0!
#1890000
b10111111 $
b10111110 %
1!
#1895000
0!
#1900000
b11000000 $
b10111111 %
1!
#1905000
0!
#1910000
b11000001 $
b11000000 %
1!
#1915000
0!
#1920000
b11000010 $
b11000001 %
1!
#1925000
0!
#1930000
b11000011 $
b11000010 %
1!
#1935000
0!
#1940000
b11000100 $
b11000011 %
1!
#1945000
0!
#1950000
b11000101 $
b11000100 %
1!
#1955000
0!
#1960000
b11000110 $
b11000101 %
1!
#1965000
0!
#1970000
b11000111 $
b11000110 %
1!
#1975000
0!
#1980000
b11001000 $
b11000111 %
1!
#1985000
0!
#1990000
b11001001 $
b11001000 %
1!
#1995000
b0 "
0#
0!
#2000000
b1 $
b0 %
1!
#2005000
b1 "
1#
0!
#2010000
b10 $
b1 %
1!
#2015000
0!
#2020000
b11 $
b10 %
1!
#2025000
0!
#2030000
b100 $
b11 %
1!
#2035000
0!
#2040000
b101 $
b100 %
1!
#2045000
0!
#2050000
b110 $
b101 %
1!
#2055000
0!
#2060000
b111 $
b110 %
1!
#2065000
0!
#2070000
b1000 $
b111 %
1!
#2075000
0!
#2080000
b1001 $
b1000 %
1!
#2085000
0!
#2090000
b1010 $
b1001 %
1!
#2095000
0!
#2100000
b1011 $
b1010 %
1!
#2105000
0!
#2110000
b1100 $
b1011 %
1!
#2115000
0!
#2120000
b1101 $
b1100 %
1!
#2125000
0!
#2130000
b1110 $
b1101 %
1!
#2135000
0!
#2140000
b1111 $
b1110 %
1!
#2145000
0!
#2150000
b10000 $
b1111 %
1!
#2155000
0!
#2160000
b10001 $
b10000 %
1!
#2165000
0!
#2170000
b10010 $
b10001 %
1!
#2175000
0!
#2180000
b10011 $
b10010 %
1!
#2185000
0!
#2190000
b10100 $
b10011 %
1!
#2195000
0!
#2200000
b10101 $
b10100 %
1!
#2205000
0!
#2210000
b10110 $
b10101 %
1!
#2215000
0!
#2220000
b10111 $
b10110 %
1!
#2225000
0!
#2230000
b11000 $
b10111 %
1!
#2235000
0!
#2240000
b11001 $
b11000 %
1!
#2245000
0!
#2250000
b11010 $
b11001 %
1!
#2255000
0!
#2260000
b11011 $
b11010 %
1!
#2265000
0!
#2270000
b11100 $
b11011 %
1!
#2275000
0!
#2280000
b11101 $
b11100 %
1!
#2285000
0!
#2290000
b11110 $
b11101 %
1!
#2295000
0!
#2300000
b11111 $
b11110 %
1!
#2305000
0!
#2310000
b100000 $
b11111 %
1!
#2315000
0!
#2320000
b100001 $
b100000 %
1!
#2325000
0!
#2330000
b100010 $
b100001 %
1!
#2335000
0!
#2340000
b100011 $
b100010 %
1!
#2345000
0!
#2350000
b100100 $
b100011 %
1!
#2355000
0!
#2360000
b100101 $
b100100 %
1!
#2365000
0!
#2370000
b100110 $
b100101 %
1!
#2375000
0!
#2380000
b100111 $
b100110 %
1!
#2385000
0!
#2390000
b101000 $
b100111 %
1!
#2395000
0!
#2400000
b101001 $
b101000 %
1!
#2405000
0!
#2410000
b101010 $
b101001 %
1!
#2415000
0!
#2420000
b101011 $
b101010 %
1!
#2425000
0!
#2430000
b101100 $
b101011 %
1!
#2435000
0!
#2440000
b101101 $
b101100 %
1!
#2445000
0!
#2450000
b101110 $
b101101 %
1!
#2455000
0!
#2460000
b101111 $
b101110 %
1!
#2465000
0!
#2470000
b110000 $
b101111 %
1!
#2475000
0!
#2480000
b110001 $
b110000 %
1!
#2485000
0!
#2490000
b110010 $
b110001 %
1!
#2495000
0!
#2500000
b110011 $
b110010 %
1!
#2505000
0!
#2510000
b110100 $
b110011 %
1!
#2515000
0!
#2520000
b110101 $
b110100 %
1!
#2525000
0!
#2530000
b110110 $
b110101 %
1!
#2535000
0!
#2540000
b110111 $
b110110 %
1!
#2545000
0!
#2550000
b111000 $
b110111 %
1!
#2555000
0!
#2560000
b111001 $
b111000 %
1!
#2565000
0!
#2570000
b111010 $
b111001 %
1!
#2575000
0!
#2580000
b111011 $
b111010 %
1!
#2585000
0!
#2590000
b111100 $
b111011 %
1!
#2595000
0!
#2600000
b111101 $
b111100 %
1!
#2605000
0!
#2610000
b111110 $
b111101 %
1!
#2615000
0!
#2620000
b111111 $
b111110 %
1!
#2625000
0!
#2630000
b1000000 $
b111111 %
1!
#2635000
0!
#2640000
b1000001 $
b1000000 %
1!
#2645000
0!
#2650000
b1000010 $
b1000001 %
1!
#2655000
0!
#2660000
b1000011 $
b1000010 %
1!
#2665000
0!
#2670000
b1000100 $
b1000011 %
1!
#2675000
0!
#2680000
b1000101 $
b1000100 %
1!
#2685000
0!
#2690000
b1000110 $
b1000101 %
1!
#2695000
0!
#2700000
b1000111 $
b1000110 %
1!
#2705000
0!
#2710000
b1001000 $
b1000111 %
1!
#2715000
0!
#2720000
b1001001 $
b1001000 %
1!
#2725000
0!
#2730000
b1001010 $
b1001001 %
1!
#2735000
0!
#2740000
b1001011 $
b1001010 %
1!
#2745000
0!
#2750000
b1001100 $
b1001011 %
1!
#2755000
0!
#2760000
b1001101 $
b1001100 %
1!
#2765000
0!
#2770000
b1001110 $
b1001101 %
1!
#2775000
0!
#2780000
b1001111 $
b1001110 %
1!
#2785000
0!
#2790000
b1010000 $
b1001111 %
1!
#2795000
0!
#2800000
b1010001 $
b1010000 %
1!
#2805000
0!
#2810000
b1010010 $
b1010001 %
1!
#2815000
0!
#2820000
b1010011 $
b1010010 %
1!
#2825000
0!
#2830000
b1010100 $
b1010011 %
1!
#2835000
0!
#2840000
b1010101 $
b1010100 %
1!
#2845000
0!
#2850000
b1010110 $
b1010101 %
1!
#2855000
0!
#2860000
b1010111 $
b1010110 %
1!
#2865000
0!
#2870000
b1011000 $
b1010111 %
1!
#2875000
0!
#2880000
b1011001 $
b1011000 %
1!
#2885000
0!
#2890000
b1011010 $
b1011001 %
1!
#2895000
0!
#2900000
b1011011 $
b1011010 %
1!
#2905000
0!
#2910000
b1011100 $
b1011011 %
1!
#2915000
0!
#2920000
b1011101 $
b1011100 %
1!
#2925000
0!
#2930000
b1011110 $
b1011101 %
1!
#2935000
0!
#2940000
b1011111 $
b1011110 %
1!
#2945000
0!
#2950000
b1100000 $
b1011111 %
1!
#2955000
0!
#2960000
b1100001 $
b1100000 %
1!
#2965000
0!
#2970000
b1100010 $
b1100001 %
1!
#2975000
0!
#2980000
b1100011 $
b1100010 %
1!
#2985000
0!
#2990000
b1100100 $
b1100011 %
1!
#2995000
0!
#3000000
b1100101 $
b1100100 %
1!
#3005000
0!
#3010000
b1100110 $
b1100101 %
1!
#3015000
0!
#3020000
b1100111 $
b1100110 %
1!
#3025000
0!
#3030000
b1101000 $
b1100111 %
1!
#3035000
0!
#3040000
b1101001 $
b1101000 %
1!
#3045000
0!
#3050000
b1101010 $
b1101001 %
1!
#3055000
0!
#3060000
b1101011 $
b1101010 %
1!
#3065000
0!
#3070000
b1101100 $
b1101011 %
1!
#3075000
0!
#3080000
b1101101 $
b1101100 %
1!
#3085000
0!
#3090000
b1101110 $
b1101101 %
1!
#3095000
0!
#3100000
b1101111 $
b1101110 %
1!
#3105000
0!
#3110000
b1110000 $
b1101111 %
1!
#3115000
0!
#3120000
b1110001 $
b1110000 %
1!
#3125000
0!
#3130000
b1110010 $
b1110001 %
1!
#3135000
0!
#3140000
b1110011 $
b1110010 %
1!
#3145000
0!
#3150000
b1110100 $
b1110011 %
1!
#3155000
0!
#3160000
b1110101 $
b1110100 %
1!
#3165000
0!
#3170000
b1110110 $
b1110101 %
1!
#3175000
0!
#3180000
b1110111 $
b1110110 %
1!
#3185000
0!
#3190000
b1111000 $
b1110111 %
1!
#3195000
0!
#3200000
b1111001 $
b1111000 %
1!
#3205000
0!
#3210000
b1111010 $
b1111001 %
1!
#3215000
0!
#3220000
b1111011 $
b1111010 %
1!
#3225000
0!
#3230000
b1111100 $
b1111011 %
1!
#3235000
0!
#3240000
b1111101 $
b1111100 %
1!
#3245000
0!
#3250000
b1111110 $
b1111101 %
1!
#3255000
0!
#3260000
b1111111 $
b1111110 %
1!
#3265000
0!
#3270000
b10000000 $
b1111111 %
1!
#3275000
0!
#3280000
b10000001 $
b10000000 %
1!
#3285000
0!
#3290000
b10000010 $
b10000001 %
1!
#3295000
0!
#3300000
b10000011 $
b10000010 %
1!
#3305000
0!
#3310000
b10000100 $
b10000011 %
1!
#3315000
0!
#3320000
b10000101 $
b10000100 %
1!
#3325000
0!
#3330000
b10000110 $
b10000101 %
1!
#3335000
0!
#3340000
b10000111 $
b10000110 %
1!
#3345000
0!
#3350000
b10001000 $
b10000111 %
1!
#3355000
0!
#3360000
b10001001 $
b10001000 %
1!
#3365000
0!
#3370000
b10001010 $
b10001001 %
1!
#3375000
0!
#3380000
b10001011 $
b10001010 %
1!
#3385000
0!
#3390000
b10001100 $
b10001011 %
1!
#3395000
0!
#3400000
b10001101 $
b10001100 %
1!
#3405000
0!
#3410000
b10001110 $
b10001101 %
1!
#3415000
0!
#3420000
b10001111 $
b10001110 %
1!
#3425000
0!
#3430000
b10010000 $
b10001111 %
1!
#3435000
0!
#3440000
b10010001 $
b10010000 %
1!
#3445000
0!
#3450000
b10010010 $
b10010001 %
1!
#3455000
0!
#3460000
b10010011 $
b10010010 %
1!
#3465000
0!
#3470000
b10010100 $
b10010011 %
1!
#3475000
0!
#3480000
b10010101 $
b10010100 %
1!
#3485000
0!
#3490000
b10010110 $
b10010101 %
1!
#3495000
0!
#3500000
b10010111 $
b10010110 %
1!
#3505000
0!
#3510000
b10011000 $
b10010111 %
1!
#3515000
0!
#3520000
b10011001 $
b10011000 %
1!
#3525000
0!
#3530000
b10011010 $
b10011001 %
1!
#3535000
0!
#3540000
b10011011 $
b10011010 %
1!
#3545000
0!
#3550000
b10011100 $
b10011011 %
1!
#3555000
0!
#3560000
b10011101 $
b10011100 %
1!
#3565000
0!
#3570000
b10011110 $
b10011101 %
1!
#3575000
0!
#3580000
b10011111 $
b10011110 %
1!
#3585000
0!
#3590000
b10100000 $
b10011111 %
1!
#3595000
0!
#3600000
b10100001 $
b10100000 %
1!
#3605000
0!
#3610000
b10100010 $
b10100001 %
1!
#3615000
0!
#3620000
b10100011 $
b10100010 %
1!
#3625000
0!
#3630000
b10100100 $
b10100011 %
1!
#3635000
0!
#3640000
b10100101 $
b10100100 %
1!
#3645000
0!
#3650000
b10100110 $
b10100101 %
1!
#3655000
0!
#3660000
b10100111 $
b10100110 %
1!
#3665000
0!
#3670000
b10101000 $
b10100111 %
1!
#3675000
0!
#3680000
b10101001 $
b10101000 %
1!
#3685000
0!
#3690000
b10101010 $
b10101001 %
1!
#3695000
0!
#3700000
b10101011 $
b10101010 %
1!
#3705000
0!
#3710000
b10101100 $
b10101011 %
1!
#3715000
0!
#3720000
b10101101 $
b10101100 %
1!
#3725000
0!
#3730000
b10101110 $
b10101101 %
1!
#3735000
0!
#3740000
b10101111 $
b10101110 %
1!
#3745000
0!
#3750000
b10110000 $
b10101111 %
1!
#3755000
0!
#3760000
b10110001 $
b10110000 %
1!
#3765000
0!
#3770000
b10110010 $
b10110001 %
1!
#3775000
0!
#3780000
b10110011 $
b10110010 %
1!
#3785000
0!
#3790000
b10110100 $
b10110011 %
1!
#3795000
0!
#3800000
b10110101 $
b10110100 %
1!
#3805000
0!
#3810000
b10110110 $
b10110101 %
1!
#3815000
0!
#3820000
b10110111 $
b10110110 %
1!
#3825000
0!
#3830000
b10111000 $
b10110111 %
1!
#3835000
0!
#3840000
b10111001 $
b10111000 %
1!
#3845000
0!
#3850000
b10111010 $
b10111001 %
1!
#3855000
0!
#3860000
b10111011 $
b10111010 %
1!
#3865000
0!
#3870000
b10111100 $
b10111011 %
1!
#3875000
0!
#3880000
b10111101 $
b10111100 %
1!
#3885000
0!
#3890000
b10111110 $
b10111101 %
1!
#3895000
0!
#3900000
b10111111 $
b10111110 %
1!
#3905000
0!
#3910000
b11000000 $
b10111111 %
1!
#3915000
0!
#3920000
b11000001 $
b11000000 %
1!
#3925000
0!
#3930000
b11000010 $
b11000001 %
1!
#3935000
0!
#3940000
b11000011 $
b11000010 %
1!
#3945000
0!
#3950000
b11000100 $
b11000011 %
1!
#3955000
0!
#3960000
b11000101 $
b11000100 %
1!
#3965000
0!
#3970000
b11000110 $
b11000101 %
1!
#3975000
0!
#3980000
b11000111 $
b11000110 %
1!
#3985000
0!
#3990000
b11001000 $
b11000111 %
1!
#3995000
0!
#4000000
b11001001 $
b11001000 %
1!
#4005000
b10 "
0!
#4010000
b1 $
b0 %
1!
