backup/primitives/register_byte/register_byte.v
/*
Module - Simple 8-bit register
Author - Zach Walden
Last Changed - 1/21/22 9:35 AM
Description - This module is a simple 8-bit register. Writes appear on the positive edge of the clock, reads occur on the negative edge of the clock.
	It takes a clock & reset signal, a write & read enable signal, and has to data ports, 8-bits in, and 8 bits out.
*/

//The testbench has verified that reset and write_enable do not conflict due to the if statement hierarchy. This may induce latency, but this latency is unlikely to be in the system's critical path.

module register_byte(
	input clock,
	input nreset,
	input write_enable,
	input [7:0] data_in,
	output [7:0] data_out
);

	reg [7:0] value = 0;

	always @ (posedge clock)
	begin
		if(nreset == 1'b0)
		begin
			value <= 0;
		end
		else if(write_enable == 1'b1)
		begin
			value <= data_in;
		end
		else
		begin
			value <= value;
		end
	end

	assign data_out = value;
/*
// the "macro" to dump signals
`ifdef COCOTB_SIM
initial begin
  $dumpfile ("register_byte.vcd");
  $dumpvars (0, register_byte);
  #1;
end
`endif
*/
endmodule

backup/primitives/register_short/register_short.v
/*
Module -
Author - Zach Walden
Last Changed -
Description -
Parameters -
*/

module register_short(
	input clock,
	input nreset,
	input [1:0] wen,
	input [1:0] ren,
	input [15:0] data_in,
	output [15:0] data_out
);
	wire [15:0] data;
	reg [1:0] read_en = 0;

	//Instantiate two 8-bit registers.
	register_byte reg0(
		.clock(clock), //clock input signal
		.nreset(nreset), //active low reset signal
		.write_enable(wen[0]), //write_enable
		.data_in(data_in[7:0]), //input data
		.data_out(data[7:0]) //output data
	);
	register_byte reg1(
		.clock(clock), //clock input signal
		.nreset(nreset), //active low reset signal
		.write_enable(wen[1]), //write_enable
		.data_in(data_in[15:8]), //input data
		.data_out(data[15:8]) //output data
	);

	always @ (posedge clock)
	begin
		read_en <= 0;
	end

	always @ (negedge clock)
	begin
		read_en <= ren;
	end

	assign data_out[7:0] = read_en[0] ? data[7:0] : 8'hZZ;
	assign data_out[15:8] = read_en[1] ? data[15:8] : 8'hZZ;

// the "macro" to dump signals
`ifdef COCOTB_SIM
initial begin
  $dumpfile ("register_short.vcd");
  $dumpvars (0, register_short);
  #1;
end
`endif
endmodule

backup/primitives/register_short/register_short.vcd
$date
	Fri Feb  4 19:02:49 2022
$end
$version
	Icarus Verilog
$end
$timescale
	1ps
$end
$scope module register_short $end
$var wire 1 ! clock $end
$var wire 16 " data_in [15:0] $end
$var wire 1 # nreset $end
$var wire 2 $ ren [1:0] $end
$var wire 2 % wen [1:0] $end
$var wire 16 & data_out [15:0] $end
$var wire 16 ' data [15:0] $end
$var reg 2 ( read_en [1:0] $end
$scope module reg0 $end
$var wire 1 ! clock $end
$var wire 8 ) data_in [7:0] $end
$var wire 1 # nreset $end
$var wire 1 * write_enable $end
$var wire 8 + data_out [7:0] $end
$var reg 8 , value [7:0] $end
$upscope $end
$scope module reg1 $end
$var wire 1 ! clock $end
$var wire 8 - data_in [7:0] $end
$var wire 1 # nreset $end
$var wire 1 . write_enable $end
$var wire 8 / data_out [7:0] $end
$var reg 8 0 value [7:0] $end
$upscope $end
$upscope $end
$enddefinitions $end
#0
$dumpvars
b0 0
b0 /
0.
bz -
b0 ,
b0 +
0*
bz )
b0 (
b0 '
bz &
b0 %
b11 $
0#
bz "
1!
$end
#5000
1#
b0 &
b11 (
0!
#10000
bz &
b0 (
1!
#15000
1*
b111 )
b0 -
b1 %
b111 "
b0 &
b11 (
0!
#20000
bz &
b111 '
b111 +
b111 ,
b0 (
1!
#25000
0*
1.
b0 )
b111 -
b10 %
b11100000000 "
b111 &
b11 (
0!
#30000
bz &
b0 (
b11100000111 '
b111 /
b111 0
1!
#35000
1*
b11111000 )
b11111000 -
b11 %
b1111100011111000 "
b11100000111 &
b11 (
0!
#40000
bz &
b11111000 +
b11111000 ,
b1111100011111000 '
b11111000 /
b11111000 0
b0 (
1!
#45000
0*
0.
b0 )
b0 -
b0 %
b0 "
b1111100011111000 &
b11 (
0!
#50000
bz &
b0 (
1!
#55000
b1 $
b1111100011111000 &
b11 (
0!
#60000
bz &
b0 (
1!
#65000
b10 $
bz11111000 &
b1 (
0!
#70000
bz &
b0 (
1!
#75000
b11 $
b11111000zzzzzzzz &
b10 (
0!
#80000
bz &
b0 (
1!
#85000
b0 $
b1111100011111000 &
b11 (
0!
#90000
bz &
b0 (
1!
#95000
b1000010 )
b1000010 -
1*
1.
b100001001000010 "
b11 %
b11 $
0!
#100000
b1000010 +
b1000010 ,
b100001001000010 '
b1000010 /
b1000010 0
1!
#105000
0*
b1101001 )
b1101001 -
b10 %
b110100101101001 "
b100001001000010 &
b11 (
0!
#110000
bz &
b0 (
b110100101000010 '
b1101001 /
b1101001 0
1!
#115000
1*
0.
b1 %
b110100101000010 &
b11 (
0!
#120000
bz &
b110100101101001 '
b1101001 +
b1101001 ,
b0 (
1!
#125000
1.
b11111111 )
b11111111 -
0#
b11 %
b1111111111111111 "
b110100101101001 &
b11 (
0!
#130000
bz &
b0 (
b0 /
b0 0
b0 '
b0 +
b0 ,
1!
#135000
b0 &
b11 (
0!
#140000
bz &
b0 (
1!
#145000
b0 &
b11 (
0!
