backup/functional_units/reg_file_output_decoder/reg_file_output_decoder.v
/*
Module -
Author - Zach Walden
Last Changed -
Description -
Parameters -
*/

module reg_file_output_decoder(
	input clock,
	input [9:0] rd_addr,
	input [1:0] rd_en,
	output [31:0] ren,
	input [255:0] data_in,
	output [15:0] data_out
);

    	integer i = 0;

    	reg [15:0] data_out_int = 0;

	reg [1:0] ren_int [0:15];
	wire [15:0] data_in_int [0:15];

    	initial
    	begin
        	for (i=0;i<16;i=i+1)
        	begin
        		ren_int[i] = 0;
        	end
    	end

	wire [1:0] rd_low;
	wire [1:0] rd_high;

	always @ (posedge clock)
	begin
		//this is needed to cover an edge case when trying to read from both halves of a register pair. Without it, only the high byte read enable signal would make its way into the register file.
		if(rd_addr[3:0] == rd_addr[8:5] && rd_en == 2'b11)
		begin
			ren_int[rd_addr[3:0]] = 2'b11;
			for(i=0;i<16;i=i+1)
			begin
				if(i != rd_addr[8:5])
				begin
					ren_int[i] <= 2'b00;
				end
				else
				begin
					ren_int[i] <= ren_int[i];
				end
			end
		end
		else
		begin
			//set the read enable signals. This can be done here as downstream modules will not affect this signal, thus, it will stay valid the entire clock cycle.
			if(rd_en[0] == 1'b1)
			begin
				//Set the proper registers wen signals.
				ren_int[rd_addr[3:0]] = rd_low;
				for(i=0;i<16;i=i+1)
				begin
					if(i != rd_addr[8:5] && i != rd_addr[3:0])
					begin
						ren_int[i] <= 2'b00;
					end
					else
					begin
						ren_int[i] <= ren_int[i];
					end
				end
			end
			else
			begin
				for(i=0;i<16;i=i+1)
				begin
					if(i != rd_addr[8:5])
					begin
						ren_int[i] <= 2'b00;
					end
					else
					begin
						ren_int[i] <= ren_int[i];
					end
				end
			end
			if(rd_en[1] == 1'b1)
			begin
				//Set the proper registers wen signals.
				ren_int[rd_addr[8:5]] = rd_high;
				for(i=0;i<16;i=i+1)
				begin
					if(i != rd_addr[8:5] && i != rd_addr[3:0])
					begin
						ren_int[i] <= 2'b00;
					end
					else
					begin
						ren_int[i] <= ren_int[i];
					end
				end
			end
			else
			begin
				for(i=0;i<16;i=i+1)
				begin
					if(i != rd_addr[3:0])
					begin
						ren_int[i] <= 2'b00;
					end
					else
					begin
						ren_int[i] <= ren_int[i];
					end
				end
			end
		end
	end

	always @ (negedge clock)
	begin
		//set data since it will not be valid until the negative edge of the clock.
		if(rd_en[0] == 1'b1)
		begin
			//check rd_low, which will be an independent value relative to rd_high
			if(rd_low[0] == 1'b1)
			begin
				data_out_int[7:0] <= data_in_int[rd_addr[3:0]][7:0];
			end
			else if(rd_low[1] == 1'b1)
			begin
				data_out_int[7:0] <= data_in_int[rd_addr[3:0]][15:8];
			end
		end
		else
		begin
			data_out_int[7:0] <= 8'h00;
		end
		if(rd_en[1] == 1'b1)
		begin
			if(rd_high[0] == 1'b1)
			begin
				data_out_int[15:8] <= data_in_int[rd_addr[8:5]][7:0];
			end
			else if(rd_high[1] == 1'b1)
			begin
				data_out_int[15:8] <= data_in_int[rd_addr[8:5]][15:8];
			end
		end
		else
		begin
			data_out_int[7:0] <= 8'h00;
		end
	end

    	//Why can I not figure out how to do this with a for loop...
    	//pair address 0x0
	assign data_in_int[0] = data_in[15:0];
	assign ren[1:0] = ren_int[0];
	//pair address 0x1
	assign data_in_int[1] = data_in[31:16];
	assign ren[3:2] = ren_int[1];
	//pair address 0x2
	assign data_in_int[2] = data_in[47:32];
	assign ren[5:4] = ren_int[2];
	//pair address 0x3
	assign data_in_int[3] = data_in[63:48];
	assign ren[7:6] = ren_int[3];
	//pair address 0x4
	assign data_in_int[4] = data_in[79:64];
	assign ren[9:8] = ren_int[4];
	//pair address 0x5
	assign data_in_int[5] = data_in[95:80];
	assign ren[11:10] = ren_int[5];
	//pair address 0x6
	assign data_in_int[6] = data_in[111:96];
	assign ren[13:12] = ren_int[6];
	//pair address 0x7
	assign data_in_int[7] = data_in[127:112];
	assign ren[15:14] = ren_int[7];
	//pair address 0x8
	assign data_in_int[8] = data_in[143:128];
	assign ren[17:16] = ren_int[8];
	//pair address 0x9
	assign data_in_int[9] = data_in[159:144];
	assign ren[19:18] = ren_int[9];
	//pair address 0xa
	assign data_in_int[10] = data_in[175:160];
	assign ren[21:20] = ren_int[10];
	//pair address 0xb
	assign data_in_int[11] = data_in[191:176];
	assign ren[23:22] = ren_int[11];
	//pair address 0xc
	assign data_in_int[12] = data_in[207:192];
	assign ren[25:24] = ren_int[12];
	//pair address 0xd
	assign data_in_int[13] = data_in[223:208];
	assign ren[27:26] = ren_int[13];
	//pair address 0xe
	assign data_in_int[14] = data_in[239:224];
	assign ren[29:28] = ren_int[14];
	//pair address 0xf
	assign data_in_int[15] = data_in[255:240];
	assign ren[31:30] = ren_int[15];

    assign data_out = data_out_int;

	assign rd_low[0] = ~rd_addr[4];
	assign rd_low[1] = rd_addr[4];
	assign rd_high[0] = ~rd_addr[9];
	assign rd_high[1] = rd_addr[9];


// the "macro" to dump signals
`ifdef COCOTB_SIM
initial begin
  $dumpfile ("reg_file_output_decoder.vcd");
  $dumpvars (0, reg_file_output_decoder);
  #1;
end
`endif

endmodule

backup/functional_units/reg_file_output_decoder/reg_file_output_decoder.vcd
$date
	Sat Feb  5 19:05:51 2022
$end
$version
	Icarus Verilog
$end
$timescale
	1ps
$end
$scope module reg_file_output_decoder $end
$var wire 1 ! clock $end
$var wire 256 " data_in [255:0] $end
$var wire 16 # data_out [15:0] $end
$var wire 10 $ rd_addr [9:0] $end
$var wire 2 % rd_en [1:0] $end
$var wire 32 & ren [31:0] $end
$var wire 2 ' rd_low [1:0] $end
$var wire 2 ( rd_high [1:0] $end
$var reg 16 ) data_out_int [15:0] $end
$var integer 32 * i [31:0] $end
$upscope $end
$enddefinitions $end
#0
$dumpvars
b10000 *
b0 )
bz (
bz '
b0 &
bz %
bz $
b0 #
bz "
1!
$end
#5000
b1 '
b10 (
b11 %
b1000000000 $
b1000000100000001100000100000001010000011000000111000010000000100100001010000010110000110000001101000011101111111100010000000100010001001000010011000101000001010100010110000101110001100000011001000110100001101100011100000111010001111011111111 "
0!
#10000
b10000 *
b11 &
1!
#15000
b1111011111111 #
b1111011111111 )
0!
#20000
b10000 *
1!
#25000
b1000100001 $
b1000000100000001100000100000001010000011000000111000010000000100100001010000010110000110000001101111111110000111100010000000100010001001000010011000101000001010100010110000101110001100000011001000110100001101100011100000111011111111100011111 "
0!
#30000
b10000 *
b1100 &
1!
#35000
b1110000011101 #
b1110000011101 )
0!
#40000
b10000 *
1!
#45000
b1001000010 $
b1000000100000001100000100000001010000011000000111000010000000100100001010000010110000110011111111000011100000111100010000000100010001001000010011000101000001010100010110000101110001100000011001000110100001101100011100111111110001111000011111 "
0!
#50000
b10000 *
b110000 &
1!
#55000
b1101000011011 #
b1101000011011 )
0!
#60000
b10000 *
1!
#65000
b1001100011 $
b1000000100000001100000100000001010000011000000111000010000000100100001010000010111111111100001101000011100000111100010000000100010001001000010011000101000001010100010110000101110001100000011001000110100001101111111111000111010001111000011111 "
0!
#70000
b10000 *
b11000000 &
1!
#75000
b1100000011001 #
b1100000011001 )
0!
#80000
b10000 *
1!
#85000
b1010000100 $
b1000000100000001100000100000001010000011000000111000010000000100100001010111111110000110000001101000011100000111100010000000100010001001000010011000101000001010100010110000101110001100000011001000110101111111100011100000111010001111000011111 "
0!
#90000
b10000 *
b1100000000 &
1!
#95000
b1011000010111 #
b1011000010111 )
0!
#100000
b10000 *
1!
#105000
b1010100101 $
b1000000100000001100000100000001010000011000000111000010000000100111111111000010110000110000001101000011100000111100010000000100010001001000010011000101000001010100010110000101110001100000011001111111110001101100011100000111010001111000011111 "
0!
#110000
b10000 *
b110000000000 &
1!
#115000
b1010000010101 #
b1010000010101 )
0!
#120000
b10000 *
1!
#125000
b1011000110 $
b1000000100000001100000100000001010000011000000111000010001111111100001010000010110000110000001101000011100000111100010000000100010001001000010011000101000001010100010110000101110001100011111111000110100001101100011100000111010001111000011111 "
0!
#130000
b10000 *
b11000000000000 &
1!
#135000
b1001000010011 #
b1001000010011 )
0!
#140000
b10000 *
1!
#145000
b1011100111 $
b1000000100000001100000100000001010000011000000111111111110000100100001010000010110000110000001101000011100000111100010000000100010001001000010011000101000001010100010110000101111111111100011001000110100001101100011100000111010001111000011111 "
0!
#150000
b10000 *
b1100000000000000 &
1!
#155000
b1000000010001 #
b1000000010001 )
0!
#160000
b10000 *
1!
#165000
b1100001000 $
b1000000100000001100000100000001010000011011111111000010000000100100001010000010110000110000001101000011100000111100010000000100010001001000010011000101000001010100010110111111110001100000011001000110100001101100011100000111010001111000011111 "
0!
#170000
b10000 *
b110000000000000000 &
1!
#175000
b111000001111 #
b111000001111 )
0!
#180000
b10000 *
1!
#185000
b1100101001 $
b1000000100000001100000100000001011111111100000111000010000000100100001010000010110000110000001101000011100000111100010000000100010001001000010011000101000001010111111111000101110001100000011001000110100001101100011100000111010001111000011111 "
0!
#190000
b10000 *
b11000000000000000000 &
1!
#195000
b110000001101 #
b110000001101 )
0!
#200000
b10000 *
1!
#205000
b1101001010 $
b1000000100000001100000100111111110000011000000111000010000000100100001010000010110000110000001101000011100000111100010000000100010001001000010011000101001111111100010110000101110001100000011001000110100001101100011100000111010001111000011111 "
0!
#210000
b10000 *
b1100000000000000000000 &
1!
#215000
b101000001011 #
b101000001011 )
0!
#220000
b10000 *
1!
#225000
b1101101011 $
b1000000100000001111111111000001010000011000000111000010000000100100001010000010110000110000001101000011100000111100010000000100010001001000010011111111110001010100010110000101110001100000011001000110100001101100011100000111010001111000011111 "
0!
#230000
b10000 *
b110000000000000000000000 &
1!
#235000
b100000001001 #
b100000001001 )
0!
#240000
b10000 *
1!
#245000
b1110001100 $
b1000000101111111100000100000001010000011000000111000010000000100100001010000010110000110000001101000011100000111100010000000100010001001011111111000101000001010100010110000101110001100000011001000110100001101100011100000111010001111000011111 "
0!
#250000
b10000 *
b11000000000000000000000000 &
1!
#255000
b11000000111 #
b11000000111 )
0!
#260000
b10000 *
1!
#265000
b1110101101 $
b1111111110000001100000100000001010000011000000111000010000000100100001010000010110000110000001101000011100000111100010000000100011111111100010011000101000001010100010110000101110001100000011001000110100001101100011100000111010001111000011111 "
0!
#270000
b10000 *
b1100000000000000000000000000 &
1!
#275000
b10000000101 #
b10000000101 )
0!
#280000
b10000 *
1!
#285000
b1111001110 $
b11111111000000100000001100000100000001010000011000000111000010000000100100001010000010110000110000001101000011100000111100010000111111110001001000010011000101000001010100010110000101110001100000011001000110100001101100011100000111010001111000011111 "
0!
#290000
b10000 *
b110000000000000000000000000000 &
1!
#295000
b1000000011 #
b1000000011 )
0!
#300000
b10000 *
1!
#305000
b1111101111 $
b1111111100000001000000100000001100000100000001010000011000000111000010000000100100001010000010110000110000001101000011100000111111111111000100010001001000010011000101000001010100010110000101110001100000011001000110100001101100011100000111010001111000011111 "
0!
#310000
b10000 *
b11000000000000000000000000000000 &
1!
#315000
b1111111100000001 #
b1111111100000001 )
0!
#320000
b10000 *
1!
#325000
0!
#330000
b10000 *
1!
#335000
0!
#340000
b10000 *
1!
