src/soc/interrupt_controller/interrupt_controller.v
/*
Module -
Author - Zach Walden
Last Changed -
Description -
Parameters -
*/

module interrupt_controller(
	input clock,
	input nreset,
	//BEIGN Interupt Signals
	input vblank_int,
	input illegal_opcode_exception,
	//BEIGN Interface with Hazard Control Unit
	input [3:0] hazard_unit_state,
	output reg interrupt = 0,
	output reg [13:0] int_vec_addr = 0,
	//BEGIN Interface with SFR Conntrol Registers
	input [143:0] sfr_output
);

	reg vblankint_t = 0;
	reg vblankint_tm1 = 0;

	reg ioeint_t = 0;
	reg ioeint_tm1 = 0;

	reg state = 0;

	always @ (posedge clock)
	begin
		if(nreset == 1'b0)
		begin
			//Zero out edge detect registers
			ioeint_tm1 <= 0;
			ioeint_t <= 0;

			vblankint_tm1 <= 0;
			vblankint_t <= 0;

			interrupt <= 0;
			int_vec_addr <= 0;
		end
		else
		begin
			ioeint_tm1 = ioeint_t;
			ioeint_t = illegal_opcode_exception;

			vblankint_tm1 = vblankint_t;
			vblankint_t = vblank_int;

			if(sfr_output[0] == 1'b1 && state == 1'b0)
			begin
				//Do interrupts.
				//Always Rising Edge
				if(vblankint_t == 1'b1 && vblankint_tm1 == 1'b0)
				begin
					//Vblank Interrut
					state <= 1;
					interrupt <= 1;
					int_vec_addr <= 14'h0000;
				end
				//Always Rising Edge
				else if(ioeint_t == 1'b1 && ioeint_tm1 == 1'b0)
				begin
					//Illegal Opcode Exception
					state <= 1;
					interrupt <= 1;
					int_vec_addr <= 14'h0000;
				end
				else
				begin
					//No Interrupts
					state <= 0;
					interrupt <= 0;
					int_vec_addr <= 14'h0000;
				end
			end
			else if(sfr_output[0] == 1'b1 && state == 1'b1 && hazard_unit_state != 4'b0010)
			begin
				//Keep signals the same.
				state <= state;
				interrupt <= interrupt;
				int_vec_addr <= int_vec_addr;
			end
			else
			begin
				//No do Interrupts.
				state <= 0;
				interrupt <= 0;
				int_vec_addr <= 14'h0000;
			end
		end
	end



// the "macro" to dump signals
`ifdef COCOTB_SIM
initial begin
  $dumpfile ("interrupt_controller.vcd");
  $dumpvars (0, interrupt_controller);
  #1;
end
`endif
endmodule

src/soc/interrupt_controller/interrupt_controller.vcd
$date
	Tue Mar 29 22:08:49 2022
$end
$version
	Icarus Verilog
$end
$timescale
	1ps
$end
$scope module interrupt_controller $end
$var wire 1 ! clock $end
$var wire 4 " hazard_unit_state [3:0] $end
$var wire 1 # illegal_opcode_exception $end
$var wire 1 $ nreset $end
$var wire 144 % sfr_output [143:0] $end
$var wire 1 & vblank_int $end
$var reg 14 ' int_vec_addr [13:0] $end
$var reg 1 ( interrupt $end
$var reg 1 ) ioeint_t $end
$var reg 1 * ioeint_tm1 $end
$var reg 1 + state $end
$var reg 1 , vblankint_t $end
$var reg 1 - vblankint_tm1 $end
$upscope $end
$enddefinitions $end
#0
$dumpvars
0-
0,
0+
0*
0)
0(
b0 '
z&
b1 %
0$
z#
b0 "
1!
$end
#5000
1$
0&
0#
0!
#10000
1!
#15000
1&
0!
#20000
1(
1+
1,
1!
#25000
0!
#30000
1-
1!
#35000
b10 "
0!
#40000
0(
0+
1!
#45000
b0 "
0&
0!
#50000
0,
1!
#55000
1#
0!
#60000
1(
1+
0-
1)
1!
#65000
b10 "
0!
#70000
0(
0+
1*
1!
