backup/functional_units/alu/adder.v
/*
Module - Adder
Author - Zach Walden
Last Changed - 1/28/22
Description - Adds or subtracts two operands. This module sets all 3 flags.
Parameters - input clock - system clock
	     input nreset - system reset, active low.
	     input add_sub - 0 results in a subtraction 1 results in an addition.
	     input oe - 1 results in the devices data being output to the alu output bus. 0 high impedance.
	     input [7:0] primary_operand - speakes for itself.
	     input [7:0] secondary_operand - speaks for itself.
	     output [2:0] flags - carry, negative, and zero flags in order from most to least significant.
	     output [7:0] result - a-bit adder result.
*/

module adder(
	input clock,
	input nreset,
	input add_sub,
	input oe,
	input [7:0] primary_operand,
	input [7:0] secondary_operand,
	output [2:0] flags,
	output [7:0] result
);

	wire [2:0] flag_result;
	reg [8:0] value = 0;

	always @ (posedge clock)
	begin
		if(nreset ==1'b0)
		begin
			value <= 9'b000000000;
		end
		else
		begin
			if(add_sub == 1'b1)
			begin
				value = primary_operand + secondary_operand;
			end
			else if(add_sub == 1'b0)
			begin
				value = primary_operand - secondary_operand;
			end
			else
			begin
				value = value;
			end
		end
	end

    assign flag_result[0] = (value[7:0] == 8'h00) ? 1'b1 : 1'b0;
    assign flag_result[1] = value[7] ? 1'b1 : 1'b0;
    assign flag_result[2] = value[8];
    
	assign flags = oe ? flag_result : 3'bzzz;
	assign result = oe ? value[7:0] : 8'hZZ;

/*
// the "macro" to dump signals
`ifdef COCOTB_SIM
initial begin
  $dumpfile ("adder.vcd");
  $dumpvars (0, adder);
  #1;
end
`endif
*/
endmodule

src/Waveforms/cpu/datapath/stages/execute/alu/adder/adder.vcd
$date
	Wed Apr 27 02:25:48 2022
$end
$version
	Icarus Verilog
$end
$timescale
	1ps
$end
$scope module adder $end
$var wire 1 ! add_sub $end
$var wire 1 " clock $end
$var wire 1 # nreset $end
$var wire 1 $ oe $end
$var wire 8 % primary_operand [7:0] $end
$var wire 8 & secondary_operand [7:0] $end
$var wire 8 ' result [7:0] $end
$var wire 3 ( flags [2:0] $end
$var wire 3 ) flag_result [2:0] $end
$var reg 9 * value [8:0] $end
$upscope $end
$enddefinitions $end
#0
$dumpvars
b1 *
b0 )
b0 (
b1 '
b1 &
b0 %
1$
1#
1"
1!
$end
#5000
b10 '
b10 *
b1 %
0"
#10000
1"
#15000
b11 '
b11 *
b10 %
0"
#20000
1"
#25000
b100 '
b100 *
b11 %
0"
#30000
1"
#35000
b101 '
b101 *
b100 %
0"
#40000
1"
#45000
b110 '
b110 *
b101 %
0"
#50000
1"
#55000
b111 '
b111 *
b110 %
0"
#60000
1"
#65000
b1000 '
b1000 *
b111 %
0"
#70000
1"
#75000
b1001 '
b1001 *
b1000 %
0"
#80000
1"
#85000
b1010 '
b1010 *
b1001 %
0"
#90000
1"
#95000
b1011 '
b1011 *
b1010 %
0"
#100000
1"
#105000
b1100 '
b1100 *
b1011 %
0"
#110000
1"
#115000
b1101 '
b1101 *
b1100 %
0"
#120000
1"
#125000
b1110 '
b1110 *
b1101 %
0"
#130000
1"
#135000
b1111 '
b1111 *
b1110 %
0"
#140000
1"
#145000
b10000 '
b10000 *
b1111 %
0"
#150000
1"
#155000
b10001 '
b10001 *
b10000 %
0"
#160000
1"
#165000
b10010 '
b10010 *
b10001 %
0"
#170000
1"
#175000
b10011 '
b10011 *
b10010 %
0"
#180000
1"
#185000
b10100 '
b10100 *
b10011 %
0"
#190000
1"
#195000
b10101 '
b10101 *
b10100 %
0"
#200000
1"
#205000
b10110 '
b10110 *
b10101 %
0"
#210000
1"
#215000
b10111 '
b10111 *
b10110 %
0"
#220000
1"
#225000
b11000 '
b11000 *
b10111 %
0"
#230000
1"
#235000
b11001 '
b11001 *
b11000 %
0"
#240000
1"
#245000
b11010 '
b11010 *
b11001 %
0"
#250000
1"
#255000
b11011 '
b11011 *
b11010 %
0"
#260000
1"
#265000
b11100 '
b11100 *
b11011 %
0"
#270000
1"
#275000
b11101 '
b11101 *
b11100 %
0"
#280000
1"
#285000
b11110 '
b11110 *
b11101 %
0"
#290000
1"
#295000
b11111 '
b11111 *
b11110 %
0"
#300000
1"
#305000
b100000 '
b100000 *
b11111 %
0"
#310000
1"
#315000
b100001 '
b100001 *
b100000 %
0"
#320000
1"
#325000
b100010 '
b100010 *
b100001 %
0"
#330000
1"
#335000
b100011 '
b100011 *
b100010 %
0"
#340000
1"
#345000
b100100 '
b100100 *
b100011 %
0"
#350000
1"
#355000
b100101 '
b100101 *
b100100 %
0"
#360000
1"
#365000
b100110 '
b100110 *
b100101 %
0"
#370000
1"
#375000
b100111 '
b100111 *
b100110 %
0"
#380000
1"
#385000
b101000 '
b101000 *
b100111 %
0"
#390000
1"
#395000
b101001 '
b101001 *
b101000 %
0"
#400000
1"
#405000
b101010 '
b101010 *
b101001 %
0"
#410000
1"
#415000
b101011 '
b101011 *
b101010 %
0"
#420000
1"
#425000
b101100 '
b101100 *
b101011 %
0"
#430000
1"
#435000
b101101 '
b101101 *
b101100 %
0"
#440000
1"
#445000
b101110 '
b101110 *
b101101 %
0"
#450000
1"
#455000
b101111 '
b101111 *
b101110 %
0"
#460000
1"
#465000
b110000 '
b110000 *
b101111 %
0"
#470000
1"
#475000
b110001 '
b110001 *
b110000 %
0"
#480000
1"
#485000
b110010 '
b110010 *
b110001 %
0"
#490000
1"
#495000
b110011 '
b110011 *
b110010 %
0"
#500000
1"
#505000
b110100 '
b110100 *
b110011 %
0"
#510000
1"
#515000
b110101 '
b110101 *
b110100 %
0"
#520000
1"
#525000
b110110 '
b110110 *
b110101 %
0"
#530000
1"
#535000
b110111 '
b110111 *
b110110 %
0"
#540000
1"
#545000
b111000 '
b111000 *
b110111 %
0"
#550000
1"
#555000
b111001 '
b111001 *
b111000 %
0"
#560000
1"
#565000
b111010 '
b111010 *
b111001 %
0"
#570000
1"
#575000
b111011 '
b111011 *
b111010 %
0"
#580000
1"
#585000
b111100 '
b111100 *
b111011 %
0"
#590000
1"
#595000
b111101 '
b111101 *
b111100 %
0"
#600000
1"
#605000
b111110 '
b111110 *
b111101 %
0"
#610000
1"
#615000
b111111 '
b111111 *
b111110 %
0"
#620000
1"
#625000
b1000000 '
b1000000 *
b111111 %
0"
#630000
1"
#635000
b1000001 '
b1000001 *
b1000000 %
0"
#640000
1"
#645000
b1000010 '
b1000010 *
b1000001 %
0"
#650000
1"
#655000
b1000011 '
b1000011 *
b1000010 %
0"
#660000
1"
#665000
b1000100 '
b1000100 *
b1000011 %
0"
#670000
1"
#675000
b1000101 '
b1000101 *
b1000100 %
0"
#680000
1"
#685000
b1000110 '
b1000110 *
b1000101 %
0"
#690000
1"
#695000
b1000111 '
b1000111 *
b1000110 %
0"
#700000
1"
#705000
b1001000 '
b1001000 *
b1000111 %
0"
#710000
1"
#715000
b1001001 '
b1001001 *
b1001000 %
0"
#720000
1"
#725000
b1001010 '
b1001010 *
b1001001 %
0"
#730000
1"
#735000
b1001011 '
b1001011 *
b1001010 %
0"
#740000
1"
#745000
b1001100 '
b1001100 *
b1001011 %
0"
#750000
1"
#755000
b1001101 '
b1001101 *
b1001100 %
0"
#760000
1"
#765000
b1001110 '
b1001110 *
b1001101 %
0"
#770000
1"
#775000
b1001111 '
b1001111 *
b1001110 %
0"
#780000
1"
#785000
b1010000 '
b1010000 *
b1001111 %
0"
#790000
1"
#795000
b1010001 '
b1010001 *
b1010000 %
0"
#800000
1"
#805000
b1010010 '
b1010010 *
b1010001 %
0"
#810000
1"
#815000
b1010011 '
b1010011 *
b1010010 %
0"
#820000
1"
#825000
b1010100 '
b1010100 *
b1010011 %
0"
#830000
1"
#835000
b1010101 '
b1010101 *
b1010100 %
0"
#840000
1"
#845000
b1010110 '
b1010110 *
b1010101 %
0"
#850000
1"
#855000
b1010111 '
b1010111 *
b1010110 %
0"
#860000
1"
#865000
b1011000 '
b1011000 *
b1010111 %
0"
#870000
1"
#875000
b1011001 '
b1011001 *
b1011000 %
0"
#880000
1"
#885000
b1011010 '
b1011010 *
b1011001 %
0"
#890000
1"
#895000
b1011011 '
b1011011 *
b1011010 %
0"
#900000
1"
#905000
b1011100 '
b1011100 *
b1011011 %
0"
#910000
1"
#915000
b1011101 '
b1011101 *
b1011100 %
0"
#920000
1"
#925000
b1011110 '
b1011110 *
b1011101 %
0"
#930000
1"
#935000
b1011111 '
b1011111 *
b1011110 %
0"
#940000
1"
#945000
b1100000 '
b1100000 *
b1011111 %
0"
#950000
1"
#955000
b1100001 '
b1100001 *
b1100000 %
0"
#960000
1"
#965000
b1100010 '
b1100010 *
b1100001 %
0"
#970000
1"
#975000
b1100011 '
b1100011 *
b1100010 %
0"
#980000
1"
#985000
b1100100 '
b1100100 *
b1100011 %
0"
#990000
1"
#995000
b1100101 '
b1100101 *
b1100100 %
0"
#1000000
1"
#1005000
b1100110 '
b1100110 *
b1100101 %
0"
#1010000
1"
#1015000
b1100111 '
b1100111 *
b1100110 %
0"
#1020000
1"
#1025000
b1101000 '
b1101000 *
b1100111 %
0"
#1030000
1"
#1035000
b1101001 '
b1101001 *
b1101000 %
0"
#1040000
1"
#1045000
b1101010 '
b1101010 *
b1101001 %
0"
#1050000
1"
#1055000
b1101011 '
b1101011 *
b1101010 %
0"
#1060000
1"
#1065000
b1101100 '
b1101100 *
b1101011 %
0"
#1070000
1"
#1075000
b1101101 '
b1101101 *
b1101100 %
0"
#1080000
1"
#1085000
b1101110 '
b1101110 *
b1101101 %
0"
#1090000
1"
#1095000
b1101111 '
b1101111 *
b1101110 %
0"
#1100000
1"
#1105000
b1110000 '
b1110000 *
b1101111 %
0"
#1110000
1"
#1115000
b1110001 '
b1110001 *
b1110000 %
0"
#1120000
1"
#1125000
b1110010 '
b1110010 *
b1110001 %
0"
#1130000
1"
#1135000
b1110011 '
b1110011 *
b1110010 %
0"
#1140000
1"
#1145000
b1110100 '
b1110100 *
b1110011 %
0"
#1150000
1"
#1155000
b1110101 '
b1110101 *
b1110100 %
0"
#1160000
1"
#1165000
b1110110 '
b1110110 *
b1110101 %
0"
#1170000
1"
#1175000
b1110111 '
b1110111 *
b1110110 %
0"
#1180000
1"
#1185000
b1111000 '
b1111000 *
b1110111 %
0"
#1190000
1"
#1195000
b1111001 '
b1111001 *
b1111000 %
0"
#1200000
1"
#1205000
b1111010 '
b1111010 *
b1111001 %
0"
#1210000
1"
#1215000
b1111011 '
b1111011 *
b1111010 %
0"
#1220000
1"
#1225000
b1111100 '
b1111100 *
b1111011 %
0"
#1230000
1"
#1235000
b1111101 '
b1111101 *
b1111100 %
0"
#1240000
1"
#1245000
b1111110 '
b1111110 *
b1111101 %
0"
#1250000
1"
#1255000
b1111111 '
b1111111 *
b1111110 %
0"
#1260000
1"
#1265000
b10 (
b10 )
b10000000 '
b10000000 *
b1111111 %
0"
#1270000
1"
#1275000
b10000001 '
b10000001 *
b10000000 %
0"
#1280000
1"
#1285000
b10000010 '
b10000010 *
b10000001 %
0"
#1290000
1"
#1295000
b10000011 '
b10000011 *
b10000010 %
0"
#1300000
1"
#1305000
b10000100 '
b10000100 *
b10000011 %
0"
#1310000
1"
#1315000
b10000101 '
b10000101 *
b10000100 %
0"
#1320000
1"
#1325000
b10000110 '
b10000110 *
b10000101 %
0"
#1330000
1"
#1335000
b10000111 '
b10000111 *
b10000110 %
0"
#1340000
1"
#1345000
b10001000 '
b10001000 *
b10000111 %
0"
#1350000
1"
#1355000
b10001001 '
b10001001 *
b10001000 %
0"
#1360000
1"
#1365000
b10001010 '
b10001010 *
b10001001 %
0"
#1370000
1"
#1375000
b10001011 '
b10001011 *
b10001010 %
0"
#1380000
1"
#1385000
b10001100 '
b10001100 *
b10001011 %
0"
#1390000
1"
#1395000
b10001101 '
b10001101 *
b10001100 %
0"
#1400000
1"
#1405000
b10001110 '
b10001110 *
b10001101 %
0"
#1410000
1"
#1415000
b10001111 '
b10001111 *
b10001110 %
0"
#1420000
1"
#1425000
b10010000 '
b10010000 *
b10001111 %
0"
#1430000
1"
#1435000
b10010001 '
b10010001 *
b10010000 %
0"
#1440000
1"
#1445000
b10010010 '
b10010010 *
b10010001 %
0"
#1450000
1"
#1455000
b10010011 '
b10010011 *
b10010010 %
0"
#1460000
1"
#1465000
b10010100 '
b10010100 *
b10010011 %
0"
#1470000
1"
#1475000
b10010101 '
b10010101 *
b10010100 %
0"
#1480000
1"
#1485000
b10010110 '
b10010110 *
b10010101 %
0"
#1490000
1"
#1495000
b10010111 '
b10010111 *
b10010110 %
0"
#1500000
1"
#1505000
b10011000 '
b10011000 *
b10010111 %
0"
#1510000
1"
#1515000
b10011001 '
b10011001 *
b10011000 %
0"
#1520000
1"
#1525000
b10011010 '
b10011010 *
b10011001 %
0"
#1530000
1"
#1535000
b10011011 '
b10011011 *
b10011010 %
0"
#1540000
1"
#1545000
b10011100 '
b10011100 *
b10011011 %
0"
#1550000
1"
#1555000
b10011101 '
b10011101 *
b10011100 %
0"
#1560000
1"
#1565000
b10011110 '
b10011110 *
b10011101 %
0"
#1570000
1"
#1575000
b10011111 '
b10011111 *
b10011110 %
0"
#1580000
1"
#1585000
b10100000 '
b10100000 *
b10011111 %
0"
#1590000
1"
#1595000
b10100001 '
b10100001 *
b10100000 %
0"
#1600000
1"
#1605000
b10100010 '
b10100010 *
b10100001 %
0"
#1610000
1"
#1615000
b10100011 '
b10100011 *
b10100010 %
0"
#1620000
1"
#1625000
b10100100 '
b10100100 *
b10100011 %
0"
#1630000
1"
#1635000
b10100101 '
b10100101 *
b10100100 %
0"
#1640000
1"
#1645000
b10100110 '
b10100110 *
b10100101 %
0"
#1650000
1"
#1655000
b10100111 '
b10100111 *
b10100110 %
0"
#1660000
1"
#1665000
b10101000 '
b10101000 *
b10100111 %
0"
#1670000
1"
#1675000
b10101001 '
b10101001 *
b10101000 %
0"
#1680000
1"
#1685000
b10101010 '
b10101010 *
b10101001 %
0"
#1690000
1"
#1695000
b10101011 '
b10101011 *
b10101010 %
0"
#1700000
1"
#1705000
b10101100 '
b10101100 *
b10101011 %
0"
#1710000
1"
#1715000
b10101101 '
b10101101 *
b10101100 %
0"
#1720000
1"
#1725000
b10101110 '
b10101110 *
b10101101 %
0"
#1730000
1"
#1735000
b10101111 '
b10101111 *
b10101110 %
0"
#1740000
1"
#1745000
b10110000 '
b10110000 *
b10101111 %
0"
#1750000
1"
#1755000
b10110001 '
b10110001 *
b10110000 %
0"
#1760000
1"
#1765000
b10110010 '
b10110010 *
b10110001 %
0"
#1770000
1"
#1775000
b10110011 '
b10110011 *
b10110010 %
0"
#1780000
1"
#1785000
b10110100 '
b10110100 *
b10110011 %
0"
#1790000
1"
#1795000
b10110101 '
b10110101 *
b10110100 %
0"
#1800000
1"
#1805000
b10110110 '
b10110110 *
b10110101 %
0"
#1810000
1"
#1815000
b10110111 '
b10110111 *
b10110110 %
0"
#1820000
1"
#1825000
b10111000 '
b10111000 *
b10110111 %
0"
#1830000
1"
#1835000
b10111001 '
b10111001 *
b10111000 %
0"
#1840000
1"
#1845000
b10111010 '
b10111010 *
b10111001 %
0"
#1850000
1"
#1855000
b10111011 '
b10111011 *
b10111010 %
0"
#1860000
1"
#1865000
b10111100 '
b10111100 *
b10111011 %
0"
#1870000
1"
#1875000
b10111101 '
b10111101 *
b10111100 %
0"
#1880000
1"
#1885000
b10111110 '
b10111110 *
b10111101 %
0"
#1890000
1"
#1895000
b10111111 '
b10111111 *
b10111110 %
0"
#1900000
1"
#1905000
b11000000 '
b11000000 *
b10111111 %
0"
#1910000
1"
#1915000
b11000001 '
b11000001 *
b11000000 %
0"
#1920000
1"
#1925000
b11000010 '
b11000010 *
b11000001 %
0"
#1930000
1"
#1935000
b11000011 '
b11000011 *
b11000010 %
0"
#1940000
1"
#1945000
b11000100 '
b11000100 *
b11000011 %
0"
#1950000
1"
#1955000
b11000101 '
b11000101 *
b11000100 %
0"
#1960000
1"
#1965000
b11000110 '
b11000110 *
b11000101 %
0"
#1970000
1"
#1975000
b11000111 '
b11000111 *
b11000110 %
0"
#1980000
1"
#1985000
b11001000 '
b11001000 *
b11000111 %
0"
#1990000
1"
#1995000
b11001001 '
b11001001 *
b11001000 %
0"
#2000000
1"
#2005000
b11001010 '
b11001010 *
b11001001 %
0"
#2010000
1"
#2015000
b11001011 '
b11001011 *
b11001010 %
0"
#2020000
1"
#2025000
b11001100 '
b11001100 *
b11001011 %
0"
#2030000
1"
#2035000
b11001101 '
b11001101 *
b11001100 %
0"
#2040000
1"
#2045000
b11001110 '
b11001110 *
b11001101 %
0"
#2050000
1"
#2055000
b11001111 '
b11001111 *
b11001110 %
0"
#2060000
1"
#2065000
b11010000 '
b11010000 *
b11001111 %
0"
#2070000
1"
#2075000
b11010001 '
b11010001 *
b11010000 %
0"
#2080000
1"
#2085000
b11010010 '
b11010010 *
b11010001 %
0"
#2090000
1"
#2095000
b11010011 '
b11010011 *
b11010010 %
0"
#2100000
1"
#2105000
b11010100 '
b11010100 *
b11010011 %
0"
#2110000
1"
#2115000
b11010101 '
b11010101 *
b11010100 %
0"
#2120000
1"
#2125000
b11010110 '
b11010110 *
b11010101 %
0"
#2130000
1"
#2135000
b11010111 '
b11010111 *
b11010110 %
0"
#2140000
1"
#2145000
b11011000 '
b11011000 *
b11010111 %
0"
#2150000
1"
#2155000
b11011001 '
b11011001 *
b11011000 %
0"
#2160000
1"
#2165000
b11011010 '
b11011010 *
b11011001 %
0"
#2170000
1"
#2175000
b11011011 '
b11011011 *
b11011010 %
0"
#2180000
1"
#2185000
b11011100 '
b11011100 *
b11011011 %
0"
#2190000
1"
#2195000
b11011101 '
b11011101 *
b11011100 %
0"
#2200000
1"
#2205000
b11011110 '
b11011110 *
b11011101 %
0"
#2210000
1"
#2215000
b11011111 '
b11011111 *
b11011110 %
0"
#2220000
1"
#2225000
b11100000 '
b11100000 *
b11011111 %
0"
#2230000
1"
#2235000
b11100001 '
b11100001 *
b11100000 %
0"
#2240000
1"
#2245000
b11100010 '
b11100010 *
b11100001 %
0"
#2250000
1"
#2255000
b11100011 '
b11100011 *
b11100010 %
0"
#2260000
1"
#2265000
b11100100 '
b11100100 *
b11100011 %
0"
#2270000
1"
#2275000
b11100101 '
b11100101 *
b11100100 %
0"
#2280000
1"
#2285000
b11100110 '
b11100110 *
b11100101 %
0"
#2290000
1"
#2295000
b11100111 '
b11100111 *
b11100110 %
0"
#2300000
1"
#2305000
b11101000 '
b11101000 *
b11100111 %
0"
#2310000
1"
#2315000
b11101001 '
b11101001 *
b11101000 %
0"
#2320000
1"
#2325000
b11101010 '
b11101010 *
b11101001 %
0"
#2330000
1"
#2335000
b11101011 '
b11101011 *
b11101010 %
0"
#2340000
1"
#2345000
b11101100 '
b11101100 *
b11101011 %
0"
#2350000
1"
#2355000
b11101101 '
b11101101 *
b11101100 %
0"
#2360000
1"
#2365000
b11101110 '
b11101110 *
b11101101 %
0"
#2370000
1"
#2375000
b11101111 '
b11101111 *
b11101110 %
0"
#2380000
1"
#2385000
b11110000 '
b11110000 *
b11101111 %
0"
#2390000
1"
#2395000
b11110001 '
b11110001 *
b11110000 %
0"
#2400000
1"
#2405000
b11110010 '
b11110010 *
b11110001 %
0"
#2410000
1"
#2415000
b11110011 '
b11110011 *
b11110010 %
0"
#2420000
1"
#2425000
b11110100 '
b11110100 *
b11110011 %
0"
#2430000
1"
#2435000
b11110101 '
b11110101 *
b11110100 %
0"
#2440000
1"
#2445000
b11110110 '
b11110110 *
b11110101 %
0"
#2450000
1"
#2455000
b11110111 '
b11110111 *
b11110110 %
0"
#2460000
1"
#2465000
b11111000 '
b11111000 *
b11110111 %
0"
#2470000
1"
#2475000
b11111001 '
b11111001 *
b11111000 %
0"
#2480000
1"
#2485000
b11111010 '
b11111010 *
b11111001 %
0"
#2490000
1"
#2495000
b11111011 '
b11111011 *
b11111010 %
0"
#2500000
1"
#2505000
b11111100 '
b11111100 *
b11111011 %
0"
#2510000
1"
#2515000
b11111101 '
b11111101 *
b11111100 %
0"
#2520000
1"
#2525000
b11111110 '
b11111110 *
b11111101 %
0"
#2530000
1"
#2535000
b11111111 '
b11111111 *
b11111110 %
0"
#2540000
1"
#2545000
b101 (
b0 '
b101 )
b100000000 *
b11111111 %
0"
#2550000
1"
#2555000
b100 (
b100 )
b10000 '
b100010000 *
0!
b0 %
b11110000 &
0"
#2560000
1"
#2565000
b10001 '
b100010001 *
b1 %
0"
#2570000
1"
#2575000
b10010 '
b100010010 *
b10 %
0"
#2580000
1"
#2585000
b10011 '
b100010011 *
b11 %
0"
#2590000
1"
#2595000
b10100 '
b100010100 *
b100 %
0"
#2600000
1"
#2605000
b10101 '
b100010101 *
b101 %
0"
#2610000
1"
#2615000
b10110 '
b100010110 *
b110 %
0"
#2620000
1"
#2625000
b10111 '
b100010111 *
b111 %
0"
#2630000
1"
#2635000
b11000 '
b100011000 *
b1000 %
0"
#2640000
1"
#2645000
b11001 '
b100011001 *
b1001 %
0"
#2650000
1"
#2655000
b11010 '
b100011010 *
b1010 %
0"
#2660000
1"
#2665000
b11011 '
b100011011 *
b1011 %
0"
#2670000
1"
#2675000
b11100 '
b100011100 *
b1100 %
0"
#2680000
1"
#2685000
b11101 '
b100011101 *
b1101 %
0"
#2690000
1"
#2695000
b11110 '
b100011110 *
b1110 %
0"
#2700000
1"
#2705000
b11111 '
b100011111 *
b1111 %
0"
#2710000
1"
#2715000
b100000 '
b100100000 *
b10000 %
0"
#2720000
1"
#2725000
b100001 '
b100100001 *
b10001 %
0"
#2730000
1"
#2735000
b100010 '
b100100010 *
b10010 %
0"
#2740000
1"
#2745000
b100011 '
b100100011 *
b10011 %
0"
#2750000
1"
#2755000
b100100 '
b100100100 *
b10100 %
0"
#2760000
1"
#2765000
b100101 '
b100100101 *
b10101 %
0"
#2770000
1"
#2775000
b100110 '
b100100110 *
b10110 %
0"
#2780000
1"
#2785000
b100111 '
b100100111 *
b10111 %
0"
#2790000
1"
#2795000
b101000 '
b100101000 *
b11000 %
0"
#2800000
1"
#2805000
b101001 '
b100101001 *
b11001 %
0"
#2810000
1"
#2815000
b101010 '
b100101010 *
b11010 %
0"
#2820000
1"
#2825000
b101011 '
b100101011 *
b11011 %
0"
#2830000
1"
#2835000
b101100 '
b100101100 *
b11100 %
0"
#2840000
1"
#2845000
b101101 '
b100101101 *
b11101 %
0"
#2850000
1"
#2855000
b101110 '
b100101110 *
b11110 %
0"
#2860000
1"
#2865000
b101111 '
b100101111 *
b11111 %
0"
#2870000
1"
#2875000
b110000 '
b100110000 *
b100000 %
0"
#2880000
1"
#2885000
b110001 '
b100110001 *
b100001 %
0"
#2890000
1"
#2895000
b110010 '
b100110010 *
b100010 %
0"
#2900000
1"
#2905000
b110011 '
b100110011 *
b100011 %
0"
#2910000
1"
#2915000
b110100 '
b100110100 *
b100100 %
0"
#2920000
1"
#2925000
b110101 '
b100110101 *
b100101 %
0"
#2930000
1"
#2935000
b110110 '
b100110110 *
b100110 %
0"
#2940000
1"
#2945000
b110111 '
b100110111 *
b100111 %
0"
#2950000
1"
#2955000
b111000 '
b100111000 *
b101000 %
0"
#2960000
1"
#2965000
b111001 '
b100111001 *
b101001 %
0"
#2970000
1"
#2975000
b111010 '
b100111010 *
b101010 %
0"
#2980000
1"
#2985000
b111011 '
b100111011 *
b101011 %
0"
#2990000
1"
#2995000
b111100 '
b100111100 *
b101100 %
0"
#3000000
1"
#3005000
b111101 '
b100111101 *
b101101 %
0"
#3010000
1"
#3015000
b111110 '
b100111110 *
b101110 %
0"
#3020000
1"
#3025000
b111111 '
b100111111 *
b101111 %
0"
#3030000
1"
#3035000
b1000000 '
b101000000 *
b110000 %
0"
#3040000
1"
#3045000
b1000001 '
b101000001 *
b110001 %
0"
#3050000
1"
#3055000
b1000010 '
b101000010 *
b110010 %
0"
#3060000
1"
#3065000
b1000011 '
b101000011 *
b110011 %
0"
#3070000
1"
#3075000
b1000100 '
b101000100 *
b110100 %
0"
#3080000
1"
#3085000
b1000101 '
b101000101 *
b110101 %
0"
#3090000
1"
#3095000
b1000110 '
b101000110 *
b110110 %
0"
#3100000
1"
#3105000
b1000111 '
b101000111 *
b110111 %
0"
#3110000
1"
#3115000
b1001000 '
b101001000 *
b111000 %
0"
#3120000
1"
#3125000
b1001001 '
b101001001 *
b111001 %
0"
#3130000
1"
#3135000
b1001010 '
b101001010 *
b111010 %
0"
#3140000
1"
#3145000
b1001011 '
b101001011 *
b111011 %
0"
#3150000
1"
#3155000
b1001100 '
b101001100 *
b111100 %
0"
#3160000
1"
#3165000
b1001101 '
b101001101 *
b111101 %
0"
#3170000
1"
#3175000
b1001110 '
b101001110 *
b111110 %
0"
#3180000
1"
#3185000
b1001111 '
b101001111 *
b111111 %
0"
#3190000
1"
#3195000
b1010000 '
b101010000 *
b1000000 %
0"
#3200000
1"
#3205000
b1010001 '
b101010001 *
b1000001 %
0"
#3210000
1"
#3215000
b1010010 '
b101010010 *
b1000010 %
0"
#3220000
1"
#3225000
b1010011 '
b101010011 *
b1000011 %
0"
#3230000
1"
#3235000
b1010100 '
b101010100 *
b1000100 %
0"
#3240000
1"
#3245000
b1010101 '
b101010101 *
b1000101 %
0"
#3250000
1"
#3255000
b1010110 '
b101010110 *
b1000110 %
0"
#3260000
1"
#3265000
b1010111 '
b101010111 *
b1000111 %
0"
#3270000
1"
#3275000
b1011000 '
b101011000 *
b1001000 %
0"
#3280000
1"
#3285000
b1011001 '
b101011001 *
b1001001 %
0"
#3290000
1"
#3295000
b1011010 '
b101011010 *
b1001010 %
0"
#3300000
1"
#3305000
b1011011 '
b101011011 *
b1001011 %
0"
#3310000
1"
#3315000
b1011100 '
b101011100 *
b1001100 %
0"
#3320000
1"
#3325000
b1011101 '
b101011101 *
b1001101 %
0"
#3330000
1"
#3335000
b1011110 '
b101011110 *
b1001110 %
0"
#3340000
1"
#3345000
b1011111 '
b101011111 *
b1001111 %
0"
#3350000
1"
#3355000
b1100000 '
b101100000 *
b1010000 %
0"
#3360000
1"
#3365000
b1100001 '
b101100001 *
b1010001 %
0"
#3370000
1"
#3375000
b1100010 '
b101100010 *
b1010010 %
0"
#3380000
1"
#3385000
b1100011 '
b101100011 *
b1010011 %
0"
#3390000
1"
#3395000
b1100100 '
b101100100 *
b1010100 %
0"
#3400000
1"
#3405000
b1100101 '
b101100101 *
b1010101 %
0"
#3410000
1"
#3415000
b1100110 '
b101100110 *
b1010110 %
0"
#3420000
1"
#3425000
b1100111 '
b101100111 *
b1010111 %
0"
#3430000
1"
#3435000
b1101000 '
b101101000 *
b1011000 %
0"
#3440000
1"
#3445000
b1101001 '
b101101001 *
b1011001 %
0"
#3450000
1"
#3455000
b1101010 '
b101101010 *
b1011010 %
0"
#3460000
1"
#3465000
b1101011 '
b101101011 *
b1011011 %
0"
#3470000
1"
#3475000
b1101100 '
b101101100 *
b1011100 %
0"
#3480000
1"
#3485000
b1101101 '
b101101101 *
b1011101 %
0"
#3490000
1"
#3495000
b1101110 '
b101101110 *
b1011110 %
0"
#3500000
1"
#3505000
b1101111 '
b101101111 *
b1011111 %
0"
#3510000
1"
#3515000
b1110000 '
b101110000 *
b1100000 %
0"
#3520000
1"
#3525000
b1110001 '
b101110001 *
b1100001 %
0"
#3530000
1"
#3535000
b1110010 '
b101110010 *
b1100010 %
0"
#3540000
1"
#3545000
b1110011 '
b101110011 *
b1100011 %
0"
#3550000
1"
#3555000
b1110100 '
b101110100 *
b1100100 %
0"
#3560000
1"
#3565000
b1110101 '
b101110101 *
b1100101 %
0"
#3570000
1"
#3575000
b1110110 '
b101110110 *
b1100110 %
0"
#3580000
1"
#3585000
b1110111 '
b101110111 *
b1100111 %
0"
#3590000
1"
#3595000
b1111000 '
b101111000 *
b1101000 %
0"
#3600000
1"
#3605000
b1111001 '
b101111001 *
b1101001 %
0"
#3610000
1"
#3615000
b1111010 '
b101111010 *
b1101010 %
0"
#3620000
1"
#3625000
b1111011 '
b101111011 *
b1101011 %
0"
#3630000
1"
#3635000
b1111100 '
b101111100 *
b1101100 %
0"
#3640000
1"
#3645000
b1111101 '
b101111101 *
b1101101 %
0"
#3650000
1"
#3655000
b1111110 '
b101111110 *
b1101110 %
0"
#3660000
1"
#3665000
b1111111 '
b101111111 *
b1101111 %
0"
#3670000
1"
#3675000
b110 (
b110 )
b10000000 '
b110000000 *
b1110000 %
0"
#3680000
1"
#3685000
b10000001 '
b110000001 *
b1110001 %
0"
#3690000
1"
#3695000
b10000010 '
b110000010 *
b1110010 %
0"
#3700000
1"
#3705000
b10000011 '
b110000011 *
b1110011 %
0"
#3710000
1"
#3715000
b10000100 '
b110000100 *
b1110100 %
0"
#3720000
1"
#3725000
b10000101 '
b110000101 *
b1110101 %
0"
#3730000
1"
#3735000
b10000110 '
b110000110 *
b1110110 %
0"
#3740000
1"
#3745000
b10000111 '
b110000111 *
b1110111 %
0"
#3750000
1"
#3755000
b10001000 '
b110001000 *
b1111000 %
0"
#3760000
1"
#3765000
b10001001 '
b110001001 *
b1111001 %
0"
#3770000
1"
#3775000
b10001010 '
b110001010 *
b1111010 %
0"
#3780000
1"
#3785000
b10001011 '
b110001011 *
b1111011 %
0"
#3790000
1"
#3795000
b10001100 '
b110001100 *
b1111100 %
0"
#3800000
1"
#3805000
b10001101 '
b110001101 *
b1111101 %
0"
#3810000
1"
#3815000
b10001110 '
b110001110 *
b1111110 %
0"
#3820000
1"
#3825000
b10001111 '
b110001111 *
b1111111 %
0"
#3830000
1"
#3835000
b10010000 '
b110010000 *
b10000000 %
0"
#3840000
1"
#3845000
b10010001 '
b110010001 *
b10000001 %
0"
#3850000
1"
#3855000
b10010010 '
b110010010 *
b10000010 %
0"
#3860000
1"
#3865000
b10010011 '
b110010011 *
b10000011 %
0"
#3870000
1"
#3875000
b10010100 '
b110010100 *
b10000100 %
0"
#3880000
1"
