src/soc/memory_io/memory_io.v
/*
Module - Memory I/O
Author - Zach Walden
Last Changed - 2/28/22
Description - Multiplexes the memory interfaces onto a single bus for the memory pipeline stage. Abstracts
Parameters -
*/

module memory_io(
	input clock,
	//BEGIN interface with the fetch pipeline stage.
	input [13:0] prog_mem_addr_fetch,
	output [31:0] prog_mem_instruction,
	//BEGIN interface with memory pipeline stage.
	input call_stk_en,
	input main_mem_en,
	input prog_mem_en,
	input fb_en,
	input mem_wen,
	input [16:0] addr_in,
	input [7:0] call_stk_addr_in,
	input [11:0] data_in,
	input [13:0] call_stk_data_in,
	output [11:0] data_out,
	output [13:0] call_stk_data_out,
	//BEGIN Interface with the call stack.
	output call_stk_wen,
	output [7:0] call_stk_addr,
	output [13:0] call_stk_din,
	input [13:0] call_stk_dout,
	//BEGIN interface with main memory
	output main_mem_wen,
	output [15:0] main_mem_addr,
	output [7:0] main_mem_din,
	input [7:0] main_mem_dout,
	//BEGIN interface with program memory.
	output [13:0] prog_mem_addra, 	//Fetch Stage
	input [31:0] prog_mem_douta,
	output [15:0] prog_mem_addrb, 	//Memory Stage
	input [7:0] prog_mem_doutb, 	//Read Only
	//BEGIN interface with the framebuffer.
	output frame_buf_wena,
	output [16:0] frame_buf_addra,
	output [11:0] frame_buf_dina,
	input [11:0] frame_buf_douta
);

	assign prog_mem_addra = prog_mem_addr_fetch;
	assign prog_mem_instruction = prog_mem_douta;

	assign call_stk_wen = mem_wen & call_stk_en;
	assign call_stk_addr = call_stk_addr_in;
	assign call_stk_din = call_stk_data_in;
	assign call_stk_data_out = call_stk_dout;

	assign main_mem_wen = mem_wen & main_mem_en;
	assign frame_buf_wena = mem_wen & fb_en;

	assign main_mem_addr = addr_in[15:0];
	assign prog_mem_addrb = addr_in[15:0];
	assign frame_buf_addra = addr_in;

	assign main_mem_din = data_in[7:0];
	assign frame_buf_dina = data_in;

	//BEGIN Data Out Multiplexing.
	assign data_out[0] = (main_mem_en & main_mem_dout[0]) | (prog_mem_en & prog_mem_doutb[0]) | (fb_en & frame_buf_douta[0]);
	assign data_out[1] = (main_mem_en & main_mem_dout[1]) | (prog_mem_en & prog_mem_doutb[1]) | (fb_en & frame_buf_douta[1]);
	assign data_out[2] = (main_mem_en & main_mem_dout[2]) | (prog_mem_en & prog_mem_doutb[2]) | (fb_en & frame_buf_douta[2]);
	assign data_out[3] = (main_mem_en & main_mem_dout[3]) | (prog_mem_en & prog_mem_doutb[3]) | (fb_en & frame_buf_douta[3]);
	assign data_out[4] = (main_mem_en & main_mem_dout[4]) | (prog_mem_en & prog_mem_doutb[4]) | (fb_en & frame_buf_douta[4]);
	assign data_out[5] = (main_mem_en & main_mem_dout[5]) | (prog_mem_en & prog_mem_doutb[5]) | (fb_en & frame_buf_douta[5]);
	assign data_out[6] = (main_mem_en & main_mem_dout[6]) | (prog_mem_en & prog_mem_doutb[6]) | (fb_en & frame_buf_douta[6]);
	assign data_out[7] = (main_mem_en & main_mem_dout[7]) | (prog_mem_en & prog_mem_doutb[7]) | (fb_en & frame_buf_douta[7]);

	assign data_out[8] = fb_en & frame_buf_douta[8];
	assign data_out[9] = fb_en & frame_buf_douta[9];
	assign data_out[10] = fb_en & frame_buf_douta[10];
	assign data_out[11] = fb_en & frame_buf_douta[11];


// the "macro" to dump signals
`ifdef COCOTB_SIM
initial begin
  $dumpfile ("memory_io.vcd");
  $dumpvars (0, memory_io);
  #1;
end
`endif
endmodule

src/soc/memory_io/memory_io.vcd
$date
	Mon Feb 28 23:46:46 2022
$end
$version
	Icarus Verilog
$end
$timescale
	1ps
$end
$scope module memory_io $end
$var wire 17 ! addr_in [16:0] $end
$var wire 8 " call_stk_addr [7:0] $end
$var wire 8 # call_stk_addr_in [7:0] $end
$var wire 14 $ call_stk_data_in [13:0] $end
$var wire 14 % call_stk_data_out [13:0] $end
$var wire 14 & call_stk_din [13:0] $end
$var wire 14 ' call_stk_dout [13:0] $end
$var wire 1 ( call_stk_en $end
$var wire 1 ) call_stk_wen $end
$var wire 1 * clock $end
$var wire 12 + data_in [11:0] $end
$var wire 1 , fb_en $end
$var wire 17 - frame_buf_addra [16:0] $end
$var wire 12 . frame_buf_dina [11:0] $end
$var wire 12 / frame_buf_douta [11:0] $end
$var wire 1 0 frame_buf_wena $end
$var wire 8 1 main_mem_dout [7:0] $end
$var wire 1 2 main_mem_en $end
$var wire 1 3 main_mem_wen $end
$var wire 1 4 mem_wen $end
$var wire 14 5 prog_mem_addr_fetch [13:0] $end
$var wire 14 6 prog_mem_addra [13:0] $end
$var wire 32 7 prog_mem_douta [31:0] $end
$var wire 8 8 prog_mem_doutb [7:0] $end
$var wire 1 9 prog_mem_en $end
$var wire 32 : prog_mem_instruction [31:0] $end
$var wire 16 ; prog_mem_addrb [15:0] $end
$var wire 8 < main_mem_din [7:0] $end
$var wire 16 = main_mem_addr [15:0] $end
$var wire 12 > data_out [11:0] $end
$upscope $end
$enddefinitions $end
#0
$dumpvars
bx >
bz =
bz <
bz ;
bz :
z9
bz 8
bz 7
bz 6
bz 5
04
03
z2
bz 1
00
bz /
bz .
bz -
z,
bz +
1*
0)
1(
b1010101010 '
b11111111111111 &
b1010101010 %
b11111111111111 $
b11111111 #
b11111111 "
bz !
$end
#5000
1)
x3
x0
14
0*
#10000
1*
#15000
0)
b11111111 <
b1111111111111111 =
b1111111111111111 ;
13
0(
b111111111111 .
b111111111111 +
b11111111111111111 -
b11111111111111111 !
12
0*
#20000
1*
#25000
03
10
02
1,
0*
#30000
1*
#35000
b11111111 >
00
0,
04
b11111111 1
b11101110 8
b110111011101 /
12
0*
#40000
1*
#45000
b11101110 >
02
19
0*
#50000
1*
#55000
b110111011101 >
09
1,
0*
#60000
1*
#65000
b0 >
0,
b1010101010 6
b1010101010 5
b11111110111111101111111011111110 :
b11111110111111101111111011111110 7
0*
