src/soc/datapath/pipeline/stages/memory/sfr_file/sfr_file.v
/* DONE
Module - Special Function Register File
Author - Zach Walden
Last Changed - 2/23/21
Description - 32 x 8 special purpose register file. This module has a single read and write port. What differentiates this module from the general purpose register file is that every single register is exposed to the entire peripheral system for reading at any time.This will be use for memory addressing, interupt control, and peripheral control. These functions, besides memory addressing, need not be defined during the design of the main CPU.

Note -
*/

module sfr_file(
	input clock,
	input nreset,
	input [6:0] mem_ptr_ctl_signals,  	//<6> Z inc, <5> Y inc, <4> X inc, <3> call stack ptr inc,<2> call stack ptr dec ,<1> stack_ptr inc,<0> stack_ptr dec
	input call_stk_addr_sel,
	input [1:0] wren,
	input [4:0] wr_addr,
	input [7:0] write_data,
	input [4:0] rd_addr,
	output [7:0] read_data,
	output reg [15:0] stack_ptr,
	output reg [15:0] x_ptr,
	output reg [15:0] y_ptr,
	output reg [15:0] z_ptr,
	output [7:0] call_stk_ptr,
	input [31:0] sfr_file_in,
	output [143:0] sfr_file_out
);

	integer i;

	reg [7:0] sfr_array [0:31];
	reg [7:0] out_data = 0;

	wire [15:0] x_intermediate;
	assign x_intermediate[15:8] = sfr_array[3];
	assign x_intermediate[7:0] = sfr_array[2];
	wire [15:0] x_inc;

	wire [15:0] y_intermediate;
	assign y_intermediate[15:8] = sfr_array[5];
	assign y_intermediate[7:0] = sfr_array[4];
	wire [15:0] y_inc;

	wire [15:0] z_intermediate;
	assign z_intermediate[15:8] = sfr_array[7];
	assign z_intermediate[7:0] = sfr_array[6];
	wire [15:0] z_inc;

	wire [15:0] stk_ptr_intermediate;
	assign stk_ptr_intermediate[15:8] = sfr_array[1];
	assign stk_ptr_intermediate[7:0] = sfr_array[0];
	wire [15:0] stk_ptr_dec;
	wire [15:0] stk_ptr_inc;

	wire [7:0] call_stk_inc;
	wire [7:0] call_stk_dec;

	initial
	begin
		for(i=0;i<32;i=i+1)
		begin
			sfr_array[i] <= 0;
		end
		stack_ptr <= 0;
		x_ptr <= 0;
		y_ptr <= 0;
		z_ptr <= 0;
	end


	always @ (posedge clock)
	begin
		if(nreset == 1'b0)
		begin
			for(i=0;i<32;i=i+1)
			begin
				sfr_array[i] <= 0;
			end
			stack_ptr <= 0;
			x_ptr <= 0;
			y_ptr <= 0;
			z_ptr <= 0;
		end
		else
		begin
			//wren[0] is write enable
			if(wren[0] == 1'b1)
			begin
				sfr_array[wr_addr] <= write_data;
			end
			else
			begin
				if(mem_ptr_ctl_signals == 7'b0000001 && wren[0] == 1'b0)
				begin
					sfr_array[0] = stk_ptr_inc[7:0];
					sfr_array[1] = stk_ptr_inc[15:8];
				end
				else if(mem_ptr_ctl_signals == 7'b0000010 && wren[0] == 1'b0)
				begin
					sfr_array[0] = stk_ptr_dec[7:0];
					sfr_array[1] = stk_ptr_dec[15:8];
				end
				else if(mem_ptr_ctl_signals == 7'b0000100 && wren[0] == 1'b0)
				begin
					sfr_array[9] = call_stk_dec;
				end
				else if(mem_ptr_ctl_signals == 7'b0001000 && wren[0] == 1'b0)
				begin
					sfr_array[9] = call_stk_inc;
				end
				else if(mem_ptr_ctl_signals == 7'b0010000 && wren[0] == 1'b0)
				begin
					sfr_array[2] = x_inc[7:0];
					sfr_array[3] = x_inc[15:8];
				end
				else if(mem_ptr_ctl_signals == 7'b0100000 && wren[0] == 1'b0)
				begin
					sfr_array[4] = y_inc[7:0];
					sfr_array[5] = y_inc[15:8];
				end
				else if(mem_ptr_ctl_signals == 7'b1000000 && wren[0] == 1'b0)
				begin
					sfr_array[6] = z_inc[7:0];
					sfr_array[7] = z_inc[15:8];
				end

							//Memory Pointers
				stack_ptr[7:0] <= sfr_array[0];
				stack_ptr[15:8] <= sfr_array[1];
				x_ptr[7:0] <= sfr_array[2];
				x_ptr[15:8] <= sfr_array[3];
				y_ptr[7:0] <= sfr_array[4];
				y_ptr[15:8] <= sfr_array[5];
				z_ptr[7:0] <= sfr_array[6];
				z_ptr[15:8] <= sfr_array[7];

				//read in input values.
				sfr_array[28] <= sfr_file_in[7:0];
				sfr_array[29] <= sfr_file_in[15:8];
				sfr_array[30] <= sfr_file_in[23:16];
				sfr_array[31] <= sfr_file_in[31:24];

			end
			if(wren[1] == 1'b1)
			begin
				out_data <= sfr_array[rd_addr];
			end
			else
			begin
				out_data <= 8'h00;
			end
		end
	end

	assign x_inc = x_intermediate + 1;
	assign y_inc = y_intermediate + 1;
	assign z_inc = z_intermediate + 1;

	assign stk_ptr_inc = stk_ptr_intermediate + 1;
	assign stk_ptr_dec = stk_ptr_intermediate - 1;

	assign call_stk_inc = sfr_array[9] + 1;
	assign call_stk_dec = sfr_array[9] - 1;

	assign call_stk_ptr = call_stk_addr_sel ? call_stk_dec : sfr_array[9];

	//Interrupt Mask Registers.
	assign sfr_file_out[7:0] = sfr_array[10]; 		//Interrupt Conntroller Control Register <0> Int Enable Flag
	assign sfr_file_out[15:8] = sfr_array[11]; 		//GICR <1> illegal_opcode_exception mask, <0> vblank_int mask
	assign sfr_file_out[23:16] = sfr_array[12];
	assign sfr_file_out[31:24] = sfr_array[13];
	//Interrupt Trigger Condition Control Registers.
	assign sfr_file_out[40:32] = sfr_array[14];
	assign sfr_file_out[48:41] = sfr_array[15];
	assign sfr_file_out[56:49] = sfr_array[16];
	assign sfr_file_out[63:57] = sfr_array[17];
	assign sfr_file_out[71:64] = sfr_array[18];
	assign sfr_file_out[79:72] = sfr_array[19];
	assign sfr_file_out[87:80] = sfr_array[20];
	assign sfr_file_out[95:88] = sfr_array[21];
	//Interupt Controller Control Registers
	assign sfr_file_out[103:96] = sfr_array[22];
	assign sfr_file_out[111:104] = sfr_array[23];
	//Output Ports
	assign sfr_file_out[119:112] = sfr_array[24];
	assign sfr_file_out[127:120] = sfr_array[25];
	assign sfr_file_out[135:128] = sfr_array[26];
	assign sfr_file_out[143:136] = sfr_array[27];
	//Memory Pointers

	assign read_data = out_data;

/*
// the "macro" to dump signals
`ifdef COCOTB_SIM
initial begin
  $dumpfile ("sfr_file.vcd");
  $dumpvars (0, sfr_file);
  #1;
end
`endif
*/
endmodule

src/soc/datapath/pipeline/stages/memory/sfr_file/sfr_file.vcd
$date
	Sat Apr 16 20:25:28 2022
$end
$version
	Icarus Verilog
$end
$timescale
	1ps
$end
$scope module sfr_file $end
$var wire 1 ! call_stk_addr_sel $end
$var wire 1 " clock $end
$var wire 7 # mem_ptr_ctl_signals [6:0] $end
$var wire 1 $ nreset $end
$var wire 5 % rd_addr [4:0] $end
$var wire 8 & read_data [7:0] $end
$var wire 32 ' sfr_file_in [31:0] $end
$var wire 5 ( wr_addr [4:0] $end
$var wire 2 ) wren [1:0] $end
$var wire 8 * write_data [7:0] $end
$var wire 16 + z_ptr [15:0] $end
$var wire 16 , z_intermediate [15:0] $end
$var wire 16 - z_inc [15:0] $end
$var wire 16 . y_ptr [15:0] $end
$var wire 16 / y_intermediate [15:0] $end
$var wire 16 0 y_inc [15:0] $end
$var wire 16 1 x_ptr [15:0] $end
$var wire 16 2 x_intermediate [15:0] $end
$var wire 16 3 x_inc [15:0] $end
$var wire 16 4 stk_ptr_intermediate [15:0] $end
$var wire 16 5 stk_ptr_inc [15:0] $end
$var wire 16 6 stk_ptr_dec [15:0] $end
$var wire 16 7 stack_ptr [15:0] $end
$var wire 144 8 sfr_file_out [143:0] $end
$var wire 8 9 call_stk_ptr [7:0] $end
$var wire 8 : call_stk_inc [7:0] $end
$var wire 8 ; call_stk_dec [7:0] $end
$var reg 8 < out_data [7:0] $end
$var integer 32 = i [31:0] $end
$upscope $end
$enddefinitions $end
#0
$dumpvars
b100000 =
b0 <
b11111111 ;
b1 :
bx 9
b0 8
b0 7
b1111111111111111 6
b1 5
b0 4
b1 3
b0 2
b0 1
b1 0
b0 /
b0 .
b1 -
b0 ,
b0 +
bz *
bz )
bz (
bz '
b0 &
bz %
0$
bz #
1"
z!
$end
#5000
1$
b100000 =
0"
#10000
1"
#15000
b0 '
b10 )
b0 %
0"
#20000
1"
#25000
b1 %
0"
#30000
1"
#35000
b10 %
0"
#40000
1"
#45000
b11 %
0"
#50000
1"
#55000
b100 %
0"
#60000
1"
#65000
b101 %
0"
#70000
1"
#75000
b110 %
0"
#80000
1"
#85000
b111 %
0"
#90000
1"
#95000
b1000 %
0"
#100000
1"
#105000
b1001 %
0"
#110000
1"
#115000
b1010 %
0"
#120000
1"
#125000
b1011 %
0"
#130000
1"
#135000
b1100 %
0"
#140000
1"
#145000
b1101 %
0"
#150000
1"
#155000
b1110 %
0"
#160000
1"
#165000
b1111 %
0"
#170000
1"
#175000
b10000 %
0"
#180000
1"
#185000
b10001 %
0"
#190000
1"
#195000
b10010 %
0"
#200000
1"
#205000
b10011 %
0"
#210000
1"
#215000
b10100 %
0"
#220000
1"
#225000
b10101 %
0"
#230000
1"
#235000
b10110 %
0"
#240000
1"
#245000
b10111 %
0"
#250000
1"
#255000
b11000 %
0"
#260000
1"
#265000
b11001 %
0"
#270000
1"
#275000
b11010 %
0"
#280000
1"
#285000
b11011 %
0"
#290000
1"
#295000
b11100 %
0"
#300000
1"
#305000
b11101 %
0"
#310000
1"
#315000
b11110 %
0"
#320000
1"
#325000
b11111 %
0"
#330000
1"
#335000
b11111111 '
0"
#340000
1"
#345000
b11100 %
0"
#350000
1"
#355000
b1111111100000000 '
b11111111 &
b11111111 <
0"
#360000
1"
#365000
b11101 %
0"
#370000
1"
#375000
b111111110000000000000000 '
0"
#380000
1"
#385000
b11110 %
0"
#390000
1"
#395000
b11111111000000000000000000000000 '
0"
#400000
1"
#405000
b11111 %
0"
#410000
1"
#415000
0"
#420000
1"
#425000
b1 )
b0 %
b0 (
b10101010 *
0"
#430000
1"
#435000
b10 )
b0 &
b0 <
b10101011 5
b10101001 6
b10101010 4
b10101010 7
0"
#440000
1"
#445000
b1 )
b1 %
b1 (
b10101010 &
b10101010 <
0"
#450000
1"
#455000
b10 )
b0 &
b0 <
b1010101010101011 5
b1010101010101001 6
b1010101010101010 4
b1010101010101010 7
0"
#460000
1"
#465000
b1 )
b10 %
b10 (
b10101010 &
b10101010 <
0"
#470000
1"
#475000
b10 )
b0 &
b0 <
b10101011 3
b10101010 2
b10101010 1
0"
#480000
1"
#485000
b1 )
b11 %
b11 (
b10101010 &
b10101010 <
0"
#490000
1"
#495000
b10 )
b0 &
b0 <
b1010101010101011 3
b1010101010101010 2
b1010101010101010 1
0"
#500000
1"
#505000
b1 )
b100 %
b100 (
b10101010 &
b10101010 <
0"
#510000
1"
#515000
b10 )
b0 &
b0 <
b10101011 0
b10101010 /
b10101010 .
0"
#520000
1"
#525000
b1 )
b101 %
b101 (
b10101010 &
b10101010 <
0"
#530000
1"
#535000
b10 )
b0 &
b0 <
b1010101010101011 0
b1010101010101010 /
b1010101010101010 .
0"
#540000
1"
#545000
b1 )
b110 %
b110 (
b10101010 &
b10101010 <
0"
#550000
1"
#555000
b10 )
b0 &
b0 <
b10101011 -
b10101010 ,
b10101010 +
0"
#560000
1"
#565000
b1 )
b111 %
b111 (
b10101010 &
b10101010 <
0"
#570000
1"
#575000
b10 )
b0 &
b0 <
b1010101010101011 -
b1010101010101010 ,
b1010101010101010 +
0"
#580000
1"
#585000
b1 )
b1000 %
b1000 (
b10101010 &
b10101010 <
0"
#590000
1"
#595000
b10 )
b0 &
b0 <
0"
#600000
1"
#605000
b1 )
b1001 %
b1001 (
b10101010 &
b10101010 <
0"
#610000
1"
#615000
b10 )
b101010xx 9
b0 &
b0 <
b10101011 :
b10101001 ;
0"
#620000
1"
#625000
b1 )
b1010 %
b1010 (
b10101010 &
b10101010 <
0"
#630000
1"
#635000
b10 )
b0 &
b0 <
b10101010 8
0"
#640000
1"
#645000
b1 )
b1011 %
b1011 (
b10101010 &
b10101010 <
0"
#650000
1"
#655000
b10 )
b0 &
b0 <
b1010101010101010 8
0"
#660000
1"
#665000
b1 )
b1100 %
b1100 (
b10101010 &
b10101010 <
0"
#670000
1"
#675000
b10 )
b0 &
b0 <
b101010101010101010101010 8
0"
#680000
1"
#685000
b1 )
b1101 %
b1101 (
b10101010 &
b10101010 <
0"
#690000
1"
#695000
b10 )
b0 &
b0 <
b10101010101010101010101010101010 8
0"
#700000
1"
#705000
b1 )
b1110 %
b1110 (
b10101010 &
b10101010 <
0"
#710000
1"
#715000
b10 )
b0 &
b0 <
b1010101010101010101010101010101010101010 8
0"
#720000
1"
#725000
b1 )
b1111 %
b1111 (
b10101010 &
b10101010 <
0"
#730000
1"
#735000
b10 )
b0 &
b0 <
b1010101001010101010101010101010101010101010101010 8
0"
#740000
1"
#745000
b1 )
b10000 %
b10000 (
b10101010 &
b10101010 <
0"
#750000
1"
#755000
b10 )
b0 &
b0 <
b101010101010101001010101010101010101010101010101010101010 8
0"
#760000
1"
#765000
b1 )
b10001 %
b10001 (
b10101010 &
b10101010 <
0"
#770000
1"
#775000
b10 )
b101010101010101010101001010101010101010101010101010101010101010 8
b0 &
b0 <
0"
#780000
1"
#785000
b1 )
b10010 %
b10010 (
b10101010 &
b10101010 <
0"
#790000
1"
#795000
b10 )
b0 &
b0 <
b101010100101010101010101010101001010101010101010101010101010101010101010 8
0"
#800000
1"
#805000
b1 )
b10011 %
b10011 (
b10101010 &
b10101010 <
0"
#810000
1"
#815000
b10 )
b0 &
b0 <
b10101010101010100101010101010101010101001010101010101010101010101010101010101010 8
0"
#820000
1"
#825000
b1 )
b10100 %
b10100 (
b10101010 &
b10101010 <
0"
#830000
1"
#835000
b10 )
b0 &
b0 <
b1010101010101010101010100101010101010101010101001010101010101010101010101010101010101010 8
0"
#840000
1"
#845000
b1 )
b10101 %
b10101 (
b10101010 &
b10101010 <
0"
#850000
1"
#855000
b10 )
b0 &
b0 <
b101010101010101010101010101010100101010101010101010101001010101010101010101010101010101010101010 8
0"
#860000
1"
#865000
b1 )
b10110 %
b10110 (
b10101010 &
b10101010 <
0"
#870000
1"
#875000
b10 )
b0 &
b0 <
b10101010101010101010101010101010101010100101010101010101010101001010101010101010101010101010101010101010 8
0"
#880000
1"
#885000
b1 )
b10111 %
b10111 (
b10101010 &
b10101010 <
0"
#890000
1"
#895000
b10 )
b0 &
b0 <
b1010101010101010101010101010101010101010101010100101010101010101010101001010101010101010101010101010101010101010 8
0"
#900000
1"
#905000
b1 )
b11000 %
b11000 (
b10101010 &
b10101010 <
0"
#910000
1"
#915000
b10 )
b0 &
b0 <
b101010101010101010101010101010101010101010101010101010100101010101010101010101001010101010101010101010101010101010101010 8
0"
#920000
1"
#925000
b1 )
b11001 %
b11001 (
b10101010 &
b10101010 <
0"
#930000
1"
#935000
b10 )
b0 &
b0 <
b10101010101010101010101010101010101010101010101010101010101010100101010101010101010101001010101010101010101010101010101010101010 8
0"
#940000
1"
#945000
b1 )
b11010 %
b11010 (
b10101010 &
b10101010 <
0"
#950000
1"
#955000
b10 )
b0 &
b0 <
b1010101010101010101010101010101010101010101010101010101010101010101010100101010101010101010101001010101010101010101010101010101010101010 8
0"
#960000
1"
#965000
b1 )
b11011 %
b11011 (
b10101010 &
b10101010 <
0"
#970000
1"
#975000
b10 )
b0 &
b0 <
b101010101010101010101010101010101010101010101010101010101010101010101010101010100101010101010101010101001010101010101010101010101010101010101010 8
0"
#980000
1"
#985000
b10101010 &
b10101010 <
0"
#990000
1"
#995000
b0 )
b1 #
0"
#1000000
1"
#1005000
b10 #
b0 &
b0 <
b1010101010101010 5
b1010101010101000 6
b1010101010101001 4
b1010101010101001 7
0"
#1010000
1"
#1015000
b100 #
b1010101010101011 5
b1010101010101001 6
b1010101010101010 4
b1010101010101010 7
0"
#1020000
1"
#1025000
b0 #
b1010100x 9
b10101010 :
b10101000 ;
0"
#1030000
1"
#1035000
b1000 #
0"
#1040000
1"
#1045000
b0 #
b101010xx 9
b10101011 :
b10101001 ;
0"
