src/soc/datapath/pipeline/stages/execute/alu/bitwise_logic_unit/bitwise_logic_unit.v
/*
Module - Bitwise Logic Unit
Author - Zach Walden
Last Changed - 1/25/22 11:47 PM
Description -
Parameters -
*/

module bitwise_logic_unit(
		input clock,
		input nreset,
		input oe,
		input and_or,
		input [7:0] primary_operand,
		input [7:0] secondary_operand,
		output [2:0] flags,
		output [7:0] result
);

	reg [7:0] value;
	wire [2:0] flags_result;

	always @ (*)
	begin
		if(and_or == 1'b1)
		begin
			value = primary_operand & secondary_operand;
		end
		else
		begin
			value = primary_operand | secondary_operand;
		end
	end

    assign flags_result[0] = (value == 8'h00) ? 1'b1 : 1'b0;
    assign flags_result[1] = value[7] ? 1'b1 : 1'b0;
    assign flags_result[2] = 0;  //there will never be a carry set when performing bitwise logic.

	assign result = oe ? value : 8'hZZ;
	assign flags = oe ? flags_result : 3'bzzz;

/*
// the "macro" to dump signals
`ifdef COCOTB_SIM
initial begin
  $dumpfile ("bitwise_logic_unit.vcd");
  $dumpvars (0, bitwise_logic_unit);
  #1;
end
`endif
*/
endmodule

src/soc/datapath/pipeline/stages/execute/alu/bit_shifter/bit_shifter.v
/*
Module -
Author - Zach Walden
Last Changed -
Description -
Parameters -
*/

module bit_shifter(
	input clock,
	input nreset,
	inout oe,
	input right_left,
	input [7:0] primary_operand,
	output [2:0] flags,
	output [7:0] result
);

    integer Index;

	wire [2:0] flags_value;
	reg [7:0] value;

	always @ (*)
	begin
		if(right_left == 1'b1)
		begin
			//shift right
			value[6:0] <= primary_operand[7:1];
			value[7] <= 1'b0;
		end
		else if (right_left == 1'b0)
		begin
			//shift left
			value[7:1] <= primary_operand[6:0];
			value[0] <= 1'b0;
		end
	end

	//assign the zero flag
    assign flags_value[0] = (value[7:0] == 8'h00) ? 1'b1 : 1'b0;
    //assign the negative flag
    assign flags_value[1] = value[7] ? 1'b1 : 1'b0;
    //if shift left carry flag == high bit, if shift right, carry flag = low bit. both of the input operand.
    assign flags_value[2] = (primary_operand[7] & ~right_left) | (primary_operand[0] & right_left);

	assign result = oe ? value : 8'hZZ;
	assign flags = oe ? flags_value : 3'bzzz;

/*
// the "macro" to dump signals
`ifdef COCOTB_SIM
initial begin
  $dumpfile ("bit_shifter.vcd");
  $dumpvars (0, bit_shifter);
  #1;
end
`endif
*/
endmodule

src/soc/datapath/pipeline/stages/execute/alu/multiplier/multiplier.v
/*
Module - Multiplier
Author - Zach Walden
Last Changed - 1/24/22 10:02 PM
Description - This module multiplies two 8-bit operands and produces a 16-bit result. It also checks & set the zero and negative flag accordingly.
Parameters - 	input [7:0] primary_operand - primary operand
		input [7:0] secondary_operand - secondary operand
		input enable - unit enable signal. This comes from the alu operation decode logic, it it asyncronous and is assumed to be valid on the rising edge of hte devices clock.
		output [2:0] flags - condition flags. This unit only accesses the zero flag - flags[0], and the negative flag - flags[1].
		output [7:0] result_low - This is the least significant byte of the result of multiplication.
		output [7:0] result_high - This is the most significant byte of the multiplication.
*/

module multiplier(
	input clock,
	input nreset,
	input [7:0] primary_operand,
	input [7:0] secondary_operand,
	input oe,
	output [2:0] flags,
	output [15:0] mult_out
);

	reg [15:0] result;
	wire [2:0] flags_result;

	always @ (*)
	begin
		result <= primary_operand * secondary_operand;
	end

    assign flags_result[0] = (result == 16'h0000) ? 1'b1 : 1'b0;
    assign flags_result[1] = result[15] ? 1'b1 : 1'b0;
    assign flags_result[2] = 0;

	assign flags = oe ? flags_result : 3'bzzz;
	assign mult_out = oe ? result : 16'h00ZZ; //high byte is set to zero for 2 reasons, potential metastability that should be eliminated by control signals, and for my testbenches.

/*
// the "macro" to dump signals
`ifdef COCOTB_SIM
initial begin
  $dumpfile ("multiplier.vcd");
  $dumpvars (0, multiplier);
  #1;
end
`endif
*/
endmodule

src/soc/datapath/pipeline/stages/execute/alu/adder/adder.v
/*
Module - Adder
Author - Zach Walden
Last Changed - 1/28/22
Description - Adds or subtracts two operands. This module sets all 3 flags.
Parameters - input clock - system clock
	     input nreset - system reset, active low.
	     input add_sub - 0 results in a subtraction 1 results in an addition.
	     input oe - 1 results in the devices data being output to the alu output bus. 0 high impedance.
	     input [7:0] primary_operand - speakes for itself.
	     input [7:0] secondary_operand - speaks for itself.
	     output [2:0] flags - carry, negative, and zero flags in order from most to least significant.
	     output [7:0] result - a-bit adder result.
*/

module adder(
	input clock,
	input nreset,
	input add_sub,
	input oe,
	input [7:0] primary_operand,
	input [7:0] secondary_operand,
	output [2:0] flags,
	output [7:0] result
);

	wire [2:0] flag_result;
	reg [8:0] value;

	always @ (*)
	begin
		if(add_sub == 1'b1)
		begin
			value <= primary_operand + secondary_operand;
		end
		else if(add_sub == 1'b0)
		begin
			value <= primary_operand - secondary_operand;
		end
	end

    assign flag_result[0] = (value[7:0] == 8'h00) ? 1'b1 : 1'b0;
    assign flag_result[1] = value[7] ? 1'b1 : 1'b0;
    assign flag_result[2] = value[8];

	assign flags = oe ? flag_result : 3'bzzz;
	assign result = oe ? value[7:0] : 8'hZZ;

/*
// the "macro" to dump signals
`ifdef COCOTB_SIM
initial begin
  $dumpfile ("adder.vcd");
  $dumpvars (0, adder);
  #1;
end
`endif
*/
endmodule

src/soc/datapath/pipeline/stages/execute/alu/alu.v


module alu(
	input clock,
	input nreset,
	input alu_operation_select,
	input [1:0] alu_operation,
	input [7:0] top_operand,
	input [7:0] bottom_operand,
	output [2:0] alu_flags,
	output [15:0] alu_out
	);

	wire [3:0] fu_oe;

	//Instantiate Adder, Multiplier, Shifter, & Bit Manipulator.
	adder add_unit(
		.clock(clock),
		.nreset(nreset),
		.add_sub(alu_operation_select),
		.oe(fu_oe[0]),
		.primary_operand(top_operand),
		.secondary_operand(bottom_operand),
		.flags(alu_flags),
		.result(alu_out[7:0])
		);

	multiplier multiply_unit(
		.clock(clock),
		.nreset(nreset),
		.oe(fu_oe[1]),
		.primary_operand(top_operand),
		.secondary_operand(bottom_operand),
		.flags(alu_flags),
		.mult_out(alu_out)
		);

	bit_shifter shifter(
		.clock(clock),
		.nreset(nreset),
		.oe(fu_oe[2]),
		.right_left(alu_operation_select),
		.primary_operand(top_operand),
		.flags(alu_flags),
		.result(alu_out[7:0])
		);

	bitwise_logic_unit bitwise(
		.clock(clock),
		.nreset(nreset),
		.oe(fu_oe[3]),
		.and_or(alu_operation_select),
		.primary_operand(top_operand),
		.secondary_operand(bottom_operand),
		.flags(alu_flags),
		.result(alu_out[7:0])
		);

	//adder oe.
	assign fu_oe[0] = ~alu_operation[0] & ~alu_operation[1];
	//multiplier oe
	assign fu_oe[1] = ~alu_operation[0] & alu_operation[1];
	//bit shifter oe
	assign fu_oe[2] = alu_operation[0] & ~alu_operation[1];
	//bitwise logic oe
	assign fu_oe[3] = alu_operation[0] & alu_operation[1];

/*
// the "macro" to dump signals
`ifdef COCOTB_SIM
initial begin
  $dumpfile ("alu.vcd");
  $dumpvars (0, alu);
  #1;
end
`endif
*/
endmodule

src/soc/datapath/pipeline/stages/execute/alu/alu.vcd
$date
	Tue Apr 12 23:38:31 2022
$end
$version
	Icarus Verilog
$end
$timescale
	1ps
$end
$scope module alu $end
$var wire 3 ! alu_flags [2:0] $end
$var wire 2 " alu_operation [1:0] $end
$var wire 1 # alu_operation_select $end
$var wire 16 $ alu_out [15:0] $end
$var wire 8 % bottom_operand [7:0] $end
$var wire 1 & clock $end
$var wire 4 ' fu_oe [3:0] $end
$var wire 1 ( nreset $end
$var wire 8 ) top_operand [7:0] $end
$scope module add_unit $end
$var wire 1 # add_sub $end
$var wire 1 & clock $end
$var wire 3 * flags [2:0] $end
$var wire 1 ( nreset $end
$var wire 1 + oe $end
$var wire 8 , primary_operand [7:0] $end
$var wire 8 - secondary_operand [7:0] $end
$var wire 8 . result [7:0] $end
$var wire 3 / flag_result [2:0] $end
$var reg 9 0 value [8:0] $end
$upscope $end
$scope module bitwise $end
$var wire 1 # and_or $end
$var wire 1 & clock $end
$var wire 3 1 flags [2:0] $end
$var wire 1 ( nreset $end
$var wire 1 2 oe $end
$var wire 8 3 primary_operand [7:0] $end
$var wire 8 4 secondary_operand [7:0] $end
$var wire 8 5 result [7:0] $end
$var wire 3 6 flags_result [2:0] $end
$var reg 8 7 value [7:0] $end
$upscope $end
$scope module multiply_unit $end
$var wire 1 & clock $end
$var wire 3 8 flags [2:0] $end
$var wire 16 9 mult_out [15:0] $end
$var wire 1 ( nreset $end
$var wire 1 : oe $end
$var wire 8 ; primary_operand [7:0] $end
$var wire 8 < secondary_operand [7:0] $end
$var wire 3 = flags_result [2:0] $end
$var reg 16 > result [15:0] $end
$upscope $end
$scope module shifter $end
$var wire 1 & clock $end
$var wire 3 ? flags [2:0] $end
$var wire 1 ( nreset $end
$var wire 1 @ oe $end
$var wire 8 A primary_operand [7:0] $end
$var wire 1 # right_left $end
$var wire 8 B result [7:0] $end
$var wire 3 C flags_value [2:0] $end
$var reg 8 D value [7:0] $end
$var integer 32 E Index [31:0] $end
$upscope $end
$upscope $end
$enddefinitions $end
#0
$dumpvars
bx E
b0 D
bx01 C
bx B
bz A
x@
bx ?
bx >
b0xx =
bz <
bz ;
x:
bx 9
bx 8
bx 7
b0xx 6
bx 5
bz 4
bz 3
x2
bx 1
b0 0
b1 /
bx .
bz -
bz ,
x+
bx *
bz )
1(
bx '
1&
bz %
bx $
z#
bz "
bx !
$end
#5000
b1 !
b1 *
b1 1
b1 8
b1 ?
b0 .
1+
b0 $
b0 9
bz 5
bz B
0:
02
0@
b1 '
b101 C
b0 "
b11111111 )
b11111111 ,
b11111111 3
b11111111 ;
b11111111 A
b1 %
b1 -
b1 4
b1 <
1#
0&
#10000
b101 !
b101 *
b101 1
b101 8
b101 ?
b0 6
b100 C
b0 =
b101 /
b1 7
b110 E
b1111111 D
b11111111 >
b100000000 0
1&
#15000
b0 C
b1111110 )
b1111110 ,
b1111110 3
b1111110 ;
b1111110 A
0&
#20000
b0 !
b0 *
b0 1
b0 8
b0 ?
b1111111 $
b1111111 9
b1111111 .
b0 /
b1 6
b1111111 0
b1111110 >
b110 E
b1111111 D
b0 7
1&
#25000
b100 C
b11111111 )
b11111111 ,
b11111111 3
b11111111 ;
b11111111 A
b0 %
b0 -
b0 4
b0 <
0&
#30000
b10 !
b10 *
b10 1
b10 8
b10 ?
b10 /
b11111111 $
b11111111 9
b11111111 .
b1 =
b110 E
b1111111 D
b0 >
b11111111 0
1&
#35000
b11111111 %
b11111111 -
b11111111 4
b11111111 <
0&
#40000
b110 !
b110 *
b110 1
b110 8
b110 ?
b11111110 $
b11111110 9
b11111110 .
b110 /
b10 =
b10 6
b111111110 0
b1111111000000001 >
b110 E
b1111111 D
b11111111 7
1&
#45000
b0 C
0#
b1 )
b1 ,
b1 3
b1 ;
b1 A
b1 %
b1 -
b1 4
b1 <
0&
#50000
b0 6
b0 =
b1 !
b1 *
b1 1
b1 8
b1 ?
b0 $
b0 9
b0 .
b1 /
b1 7
b0 E
b10 D
b1 >
b0 0
1&
#55000
b1010 )
b1010 ,
b1010 3
b1010 ;
b1010 A
0&
#60000
b0 !
b0 *
b0 1
b0 8
b0 ?
b0 /
b1001 $
b1001 9
b1001 .
b1001 0
b1010 >
b0 E
b10100 D
b1011 7
1&
#65000
b1 )
b1 ,
b1 3
b1 ;
b1 A
b11111111 %
b11111111 -
b11111111 4
b11111111 <
0&
#70000
b10 6
b100 !
b100 *
b100 1
b100 8
b100 ?
b10 $
b10 9
b10 .
b100 /
b11111111 7
b0 E
b10 D
b11111111 >
b100000010 0
1&
#75000
b1111111 )
b1111111 ,
b1111111 3
b1111111 ;
b1111111 A
b10001111 %
b10001111 -
b10001111 4
b10001111 <
0&
#80000
b110 !
b110 *
b110 1
b110 8
b110 ?
b110 /
b11110000 $
b11110000 9
b11110000 .
b10 C
b111110000 0
b100011011110001 >
b0 E
b11111110 D
1&
#85000
b11111111 %
b11111111 -
b11111111 4
b11111111 <
0&
#90000
b10000000 $
b10000000 9
b10000000 .
b0 E
b11111110 D
b111111010000001 >
b110000000 0
1&
#95000
0&
#100000
b0 E
b11111110 D
1&
#105000
bz .
0+
b0 !
b0 *
b0 1
b0 8
b0 ?
b111111010000001 $
b111111010000001 9
1:
b10 '
b110 C
b10 "
b11111111 )
b11111111 ,
b11111111 3
b11111111 ;
b11111111 A
0&
#110000
b10 !
b10 *
b10 1
b10 8
b10 ?
b10 =
b1111111000000001 $
b1111111000000001 9
b1 /
b0 E
b11111110 D
b1111111000000001 >
b0 0
1&
#115000
b10 C
b1 )
b1 ,
b1 3
b1 ;
b1 A
0&
#120000
b0 !
b0 *
b0 1
b0 8
b0 ?
b0 =
b0 C
b100 /
b11111111 $
b11111111 9
b100000010 0
b11111111 >
b0 E
b10 D
1&
#125000
b100 C
b11111111 )
b11111111 ,
b11111111 3
b11111111 ;
b11111111 A
b0 %
b0 -
b0 4
b0 <
0&
#130000
b110 C
b1 !
b1 *
b1 1
b1 8
b1 ?
b1 =
b0 $
b0 9
b10 /
b0 E
b11111110 D
b0 >
b11111111 0
1&
#135000
b10 C
b1111 )
b1111 ,
b1111 3
b1111 ;
b1111 A
b1111 %
b1111 -
b1111 4
b1111 <
0&
#140000
b1 /
b0 !
b0 *
b0 1
b0 8
b0 ?
b0 C
b0 6
b0 =
b11100001 $
b11100001 9
b0 0
b11100001 >
b0 E
b11110 D
b1111 7
1&
#145000
b11110 $
b11110 9
b11110 B
b100 !
b100 *
b100 1
b100 8
b100 ?
0:
1@
b100 '
b100 C
b1 "
1#
b11111111 )
b11111111 ,
b11111111 3
b11111111 ;
b11111111 A
0&
#150000
b1111111 $
b1111111 9
b1111111 B
b100 /
b110 E
b1111111 D
b111011110001 >
b100001110 0
1&
#155000
b0 !
b0 *
b0 1
b0 8
b0 ?
b0 C
b11111110 )
b11111110 ,
b11111110 3
b11111110 ;
b11111110 A
0&
#160000
b100001101 0
b111011100010 >
b110 E
b1111111 D
b1110 7
1&
#165000
b100 !
b100 *
b100 1
b100 8
b100 ?
b100 C
b1 )
b1 ,
b1 3
b1 ;
b1 A
0&
#170000
b101 !
b101 *
b101 1
b101 8
b101 ?
b101 C
b0 $
b0 9
b0 B
b0 /
b1 7
b110 E
b0 D
b1111 >
b10000 0
1&
#175000
b1 !
b1 *
b1 1
b1 8
b1 ?
b1 C
b0 )
b0 ,
b0 3
b0 ;
b0 A
0&
#180000
b1 =
b1 6
b1111 0
b0 >
b110 E
b0 7
1&
#185000
b101 !
b101 *
b101 1
b101 8
b101 ?
b101 C
0#
b11111111 )
b11111111 ,
b11111111 3
b11111111 ;
b11111111 A
0&
#190000
b110 !
b110 *
b110 1
b110 8
b110 ?
b10 /
b10 6
b110 C
b11111110 $
b11111110 9
b11111110 B
b0 =
b11111111 7
b0 E
b11111110 D
b111011110001 >
b11110000 0
1&
#195000
b10 !
b10 *
b10 1
b10 8
b10 ?
b10 C
b1111111 )
b1111111 ,
b1111111 3
b1111111 ;
b1111111 A
0&
#200000
b0 /
b0 6
b1110000 0
b11101110001 >
b0 E
b11111110 D
b1111111 7
1&
#205000
b110 !
b110 *
b110 1
b110 8
b110 ?
b110 C
b10000000 )
b10000000 ,
b10000000 3
b10000000 ;
b10000000 A
0&
#210000
b10 6
b101 !
b101 *
b101 1
b101 8
b101 ?
b101 C
b0 $
b0 9
b0 B
b10001111 7
b0 E
b0 D
b11110000000 >
b1110001 0
1&
#215000
b1 !
b1 *
b1 1
b1 8
b1 ?
b1 C
b0 )
b0 ,
b0 3
b0 ;
b0 A
0&
#220000
b0 6
b110 /
b1 =
b111110001 0
b0 >
b0 E
b1111 7
1&
#225000
bz B
b1111 $
b1111 9
b1111 5
0@
12
b1000 '
b0 !
b0 *
b0 1
b0 8
b0 ?
b101 C
b11 "
1#
b11111111 )
b11111111 ,
b11111111 3
b11111111 ;
b11111111 A
0&
#230000
b100 /
b100 C
b0 =
b110 E
b1111111 D
b111011110001 >
b100001110 0
1&
#235000
b11110000 %
b11110000 -
b11110000 4
b11110000 <
0&
#240000
b10 !
b10 *
b10 1
b10 8
b10 ?
b110 /
b10 =
b10 6
b11110000 $
b11110000 9
b11110000 5
b111101111 0
b1110111100010000 >
b110 E
b1111111 D
b11110000 7
1&
#245000
b0 %
b0 -
b0 4
b0 <
0&
#250000
b1 !
b1 *
b1 1
b1 8
b1 ?
b1 6
b0 $
b0 9
b0 5
b1 =
b10 /
b0 7
b110 E
b1111111 D
b0 >
b11111111 0
1&
#255000
b100 C
0#
b11110000 )
b11110000 ,
b11110000 3
b11110000 ;
b11110000 A
b1111 %
b1111 -
b1111 4
b1111 <
0&
#260000
b110 C
b10 !
b10 *
b10 1
b10 8
b10 ?
b0 =
b10 6
b11111111 $
b11111111 9
b11111111 5
b11100001 0
b111000010000 >
b0 E
b11100000 D
b11111111 7
1&
#265000
b10 C
b0 )
b0 ,
b0 3
b0 ;
b0 A
b0 %
b0 -
b0 4
b0 <
0&
#270000
b1 !
b1 *
b1 1
b1 8
b1 ?
b1 /
b1 6
b0 $
b0 9
b0 5
b1 C
b1 =
b0 7
b0 E
b0 D
b0 >
b0 0
1&
#275000
b101010 )
b101010 ,
b101010 3
b101010 ;
b101010 A
b1010101 %
b1010101 -
b1010101 4
b1010101 <
0&
#280000
b0 !
b0 *
b0 1
b0 8
b0 ?
b110 /
b0 =
b0 C
b0 6
b1111111 $
b1111111 9
b1111111 5
b111010101 0
b110111110010 >
b0 E
b1010100 D
b1111111 7
1&
