src/soc/datapath/register_file/register_file.v
/*
Module - Register File
Author - Zach Walden
Last Changed - 4/16/22
Description - 32 8-Bit Registers 2 reads and 2 writes each cycle
Parameters -
*/

module register_file(
	input clock,
	input nreset,
	input [1:0] wr_en,
	input [1:0] rd_en,
	input [9:0] wr_addr,
	input [9:0] rd_addr,
	input [15:0] data_in,
	output [15:0] data_out
);
	integer i;

	reg [7:0] reg_file [0:31];

	initial
	begin
		for(i=0;i<32;i=i+1)
		begin
			reg_file[i] = 0;
		end
	end

	always @ (negedge clock)
	begin
		//handle writes
		if(nreset == 1'b0)
		begin
			for(i=0;i<32;i=i+1)
			begin
				reg_file[i] <= 0;
			end
		end
		else
		begin
			if(wr_en[0] == 1'b1)
			begin
				reg_file[wr_addr[4:0]] <= data_in[7:0];
			end
			/*
			else
			begin
				reg_file[wr_addr[4:0]] <= reg_file[wr_addr[4:0]];
			end
			*/
			if(wr_en[1] == 1'b1)
			begin
				reg_file[wr_addr[9:5]] <= data_in[15:8];
			end
			/*
			else
			begin
				reg_file[wr_addr[9:5]] <= reg_file[wr_addr[9:5]];
			end
			*/
		end
	end

	assign data_out[7:0] = rd_en[0] ? reg_file[rd_addr[4:0]] : 8'h00;
	assign data_out[15:8] = rd_en[1] ? reg_file[rd_addr[9:5]] : 8'h00;

/*
// the "macro" to dump signals
`ifdef COCOTB_SIM
initial begin
  $dumpfile ("register_file.vcd");
  $dumpvars (0, register_file);
  #1;
end
`endif
*/
endmodule

src/soc/datapath/register_file/register_file.vcd
$date
	Sat Apr 16 18:33:55 2022
$end
$version
	Icarus Verilog
$end
$timescale
	1ps
$end
$scope module register_file $end
$var wire 1 ! clock $end
$var wire 16 " data_in [15:0] $end
$var wire 1 # nreset $end
$var wire 10 $ rd_addr [9:0] $end
$var wire 2 % rd_en [1:0] $end
$var wire 10 & wr_addr [9:0] $end
$var wire 2 ' wr_en [1:0] $end
$var wire 16 ( data_out [15:0] $end
$var integer 32 ) i [31:0] $end
$upscope $end
$enddefinitions $end
#0
$dumpvars
b100000 )
b0 (
b1 '
b0 &
b1 %
b0 $
1#
b1 "
1!
$end
#5000
b1 (
0!
#10000
b0 (
b10 "
b1 &
b1 $
1!
#15000
b10 (
0!
#20000
b0 (
b11 "
b10 &
b10 $
1!
#25000
b11 (
0!
#30000
b0 (
b100 "
b11 &
b11 $
1!
#35000
b100 (
0!
#40000
b0 (
b101 "
b100 &
b100 $
1!
#45000
b101 (
0!
#50000
b0 (
b110 "
b101 &
b101 $
1!
#55000
b110 (
0!
#60000
b0 (
b111 "
b110 &
b110 $
1!
#65000
b111 (
0!
#70000
b0 (
b1000 "
b111 &
b111 $
1!
#75000
b1000 (
0!
#80000
b0 (
b1001 "
b1000 &
b1000 $
1!
#85000
b1001 (
0!
#90000
b0 (
b1010 "
b1001 &
b1001 $
1!
#95000
b1010 (
0!
#100000
b0 (
b1011 "
b1010 &
b1010 $
1!
#105000
b1011 (
0!
#110000
b0 (
b1100 "
b1011 &
b1011 $
1!
#115000
b1100 (
0!
#120000
b0 (
b1101 "
b1100 &
b1100 $
1!
#125000
b1101 (
0!
#130000
b0 (
b1110 "
b1101 &
b1101 $
1!
#135000
b1110 (
0!
#140000
b0 (
b1111 "
b1110 &
b1110 $
1!
#145000
b1111 (
0!
#150000
b0 (
b10000 "
b1111 &
b1111 $
1!
#155000
b10000 (
0!
#160000
b0 (
b10001 "
b10000 &
b10000 $
1!
#165000
b10001 (
0!
#170000
b0 (
b10010 "
b10001 &
b10001 $
1!
#175000
b10010 (
0!
#180000
b0 (
b10011 "
b10010 &
b10010 $
1!
#185000
b10011 (
0!
#190000
b0 (
b10100 "
b10011 &
b10011 $
1!
#195000
b10100 (
0!
#200000
b0 (
b10101 "
b10100 &
b10100 $
1!
#205000
b10101 (
0!
#210000
b0 (
b10110 "
b10101 &
b10101 $
1!
#215000
b10110 (
0!
#220000
b0 (
b10111 "
b10110 &
b10110 $
1!
#225000
b10111 (
0!
#230000
b0 (
b11000 "
b10111 &
b10111 $
1!
#235000
b11000 (
0!
#240000
b0 (
b11001 "
b11000 &
b11000 $
1!
#245000
b11001 (
0!
#250000
b0 (
b11010 "
b11001 &
b11001 $
1!
#255000
b11010 (
0!
#260000
b0 (
b11011 "
b11010 &
b11010 $
1!
#265000
b11011 (
0!
#270000
b0 (
b11100 "
b11011 &
b11011 $
1!
#275000
b11100 (
0!
#280000
b0 (
b11101 "
b11100 &
b11100 $
1!
#285000
b11101 (
0!
#290000
b0 (
b11110 "
b11101 &
b11101 $
1!
#295000
b11110 (
0!
#300000
b0 (
b11111 "
b11110 &
b11110 $
1!
#305000
b11111 (
0!
#310000
b0 (
b100000 "
b11111 &
b11111 $
1!
#315000
b100000 (
0!
#320000
b0 '
0#
1!
#325000
1#
b0 (
b100000 )
0!
#330000
b0 $
1!
#335000
0!
#340000
b1 $
1!
#345000
0!
#350000
b10 $
1!
#355000
0!
#360000
b11 $
1!
#365000
0!
#370000
b100 $
1!
#375000
0!
#380000
b101 $
1!
#385000
0!
#390000
b110 $
1!
#395000
0!
#400000
b111 $
1!
#405000
0!
#410000
b1000 $
1!
#415000
0!
#420000
b1001 $
1!
#425000
0!
#430000
b1010 $
1!
#435000
0!
#440000
b1011 $
1!
#445000
0!
#450000
b1100 $
1!
#455000
0!
#460000
b1101 $
1!
#465000
0!
#470000
b1110 $
1!
#475000
0!
#480000
b1111 $
1!
#485000
0!
#490000
b10000 $
1!
#495000
0!
#500000
b10001 $
1!
#505000
0!
#510000
b10010 $
1!
#515000
0!
#520000
b10011 $
1!
#525000
0!
#530000
b10100 $
1!
#535000
0!
#540000
b10101 $
1!
#545000
0!
#550000
b10110 $
1!
#555000
0!
#560000
b10111 $
1!
#565000
0!
#570000
b11000 $
1!
#575000
0!
#580000
b11001 $
1!
#585000
0!
#590000
b11010 $
1!
#595000
0!
#600000
b11011 $
1!
#605000
0!
#610000
b11100 $
1!
#615000
0!
#620000
b11101 $
1!
#625000
0!
#630000
b11110 $
1!
#635000
0!
#640000
b11111 $
1!
#645000
0!
#650000
0#
1!
#655000
b100000 )
0!
#660000
1#
1!
#665000
0!
#670000
b0 $
b0 &
b1111111111101110 "
1!
#675000
0!
#680000
b1 '
b10 $
b10 &
b1100110011011101 "
1!
#685000
b11011101 (
0!
#690000
b0 (
b10 '
b10 %
b100 $
b100 &
b1010101010111011 "
1!
#695000
b1010101000000000 (
0!
#700000
b11 '
b11 %
b110 $
b110 &
b1000100010011001 "
1!
#705000
b1000100010011001 (
0!
